Workbook

Sheet Lisez-moi
A1: AFN — Registre des risques et feuille de route (TP MEHARI)
A2: Version 5 du 23/10/2026 — auteurs : Kleiton KITANI, Ryan AMORY. Tableau de pilotage associé au classeur AFN_MEHARI_v04_2026-10-20.xlsm et au journal d'hypothèses v11.
A4: Objet | B4: Livrables 3 (registre des risques) et 4 (feuille de route) de l'énoncé (§6, p.4), au format des modèles du §7 (p.5–6), complétés des colonnes demandées aux étapes 23 à 27.
A5: Source des niveaux | B5: Classeur MEHARI-Standard 2022 Éd. 2.1 (v04), feuille Scénarios : colonnes L (impact intrinsèque), M (exposition), P (gravité intrinsèque), X/Y/Z (I, P, gravité calculés). Valeurs relevées sur des copies du classeur recalculées ; elles reproduisent exactement les valeurs enregistrées par Excel (Tbord du classeur rendu).
A6: « Actuel » | B6: Gravité actuelle, tenant compte de l'état actuel des services de sécurité (option 2). Elle reste égale à la gravité intrinsèque : les mesures de base existent mais ne sont ni pilotées ni vérifiées, et MEHARI les note au niveau 1 (journal O-16).
A7: « Après plan » | B7: Gravité résiduelle (option 3) du classeur rendu : 12 projets décidés (feuille Projets, col. D), niveaux cibles fixés à 3 (« correctement mis en œuvre »). Objectif à six mois : 13 scénarios retenus inacceptables sur 20, contre 19 aujourd'hui.
A8: « À terme » | B8: Même calcul sur une copie, avec les cibles d'origine du modèle, souvent 4 (« mature et documenté ») : 2 scénarios inacceptables, les acceptés de RP-6. Horizon de 12 à 18 mois.
A9: Grille de gravité | B9: Grille d'acceptabilité du classeur (onglet Gravité), identique à celle du guide (p.41). Niveau 4 : risque insupportable, mesures d'urgence ; niveau 3 : inadmissible, à réduire dans un plan ; niveaux 1–2 : tolérés (guide p.16). Grille non encore validée par la direction (M-12).
A10: Priorités | B10: Convention de l'équipe. P1 : à lancer au mois 1, terminé au plus tard au mois 2 (risque de niveau 4, incident déjà subi ou mesure d'urgence). P2 : mois 2 à 4. P3 : à partir du mois 4.
A11: Charge / coût | B11: Granularité demandée par l'énoncé (étape 25), complétée d'un ordre de grandeur (journal H-08) : Faible = outils déjà en place, au plus 3 jours-homme ; Moyen = achat ou abonnement, ou 4 à 10 jours-homme ; Élevé = projet de plusieurs mois. Jours du prestataire valorisés à 700 € HT, temps interne à 350 € chargés (coût d'opportunité). Total estimé : 74 jours-homme ; coût externe de la première année : environ 16 à 26 k€.
A12: Responsables | B12: Responsables des actions : responsable IT à temps partiel, exploitation confiée à un prestataire, référent SSI (qui porte aussi la conformité), direction, RH (journal H-11, H-26). Propriétaires des risques : des responsables métier ayant autorité (direction, direction administrative et financière, responsable pédagogique), colonne Q du registre. L'organisation réelle d'AFN reste à confirmer (M-09).
A13: Échéances | B13: Exprimées en mois après la validation du plan (M0), comme dans le modèle de l'énoncé. La date de M0 est une hypothèse, modifiable dans la cellule jaune de l'onglet Feuille de route ; les dates indicatives se recalculent.
A14: Onglets | B14: Registre prioritaire : les 8 risques prioritaires, numérotés par ordre de gravité, avec leur propriétaire. Risques résiduels : tous les scénarios qui restent au niveau 3 après le plan, retenus ou non, avec la décision proposée. Feuille de route : 19 actions, 6 lots, mesures ISO 27002, planning M1–M12 et phase 2. Scénarios retenus : les 20 scénarios analysés. Projets MEHARI : choix des 12 projets, gain calculé et candidats de la phase 2. Synthèse : comptages et évolution par mois. Scénarios exclus : les 163 autres scénarios, avec motif et gravité après plan.
A15: Couleurs | B15: Gravité 4 rouge, 3 orange, 2 jaune, 1 vert. Cellule jaune vif : seule valeur à saisir (date M0).
A16: Références | B16: Énoncé « TP MEHARI – Analyse de risques SSI » ; « Introduction aux TP » ; CLUSIF, Guide MEHARI-Standard 2022 Éd. 2 ; cours « Normes et standards » ; ISO/IEC 27001 et 27002:2022 ; journal d'hypothèses v11 (O-, H-, J-, M-, Q-).

Sheet Registre prioritaire
A1: Registre des risques prioritaires — modèle de l'énoncé (§7, p.5), colonnes A à F
A2: Colonnes G à Q : compléments demandés par les étapes 21 à 27 et par le cours (propriétaire du risque). Les niveaux sont calculés à partir de l'onglet Scénarios retenus (maximum des scénarios du risque). Risques numérotés par ordre de gravité. « Après plan » : classeur rendu, cibles à 3 ; « à terme » : copie, cibles à 4.
A4: Risque | B4: Actif / processus | C4: Scénario | D4: Niveau résiduel | E4: Décision | F4: Justification | G4: Description du scénario | H4: Scénarios MEHARI | I4: Gravité actuelle (max) | J4: Gravité après plan, cibles à 3 (max) | K4: Gravité à terme, cibles à 4 (max) | L4: Écarts de services (questionnaires) | M4: Projets MEHARI | N4: Actions (feuille de route) | O4: Conditions, surveillance, transfert | P4: Exemple de l'énoncé | Q4: Propriétaire du risque
A5: RP-1 | B5: Fichiers bureautiques (NAS, postes) ; postes de travail | C5: Logiciel malveillant : fuite de données (confidentialité) et blocage des postes | D5: ="Actuel "&I5&" ; après plan "&J5&" ; à terme "&K5 -> Actuel 4 ; après plan 3 ; à terme 2 | E5: Réduire en urgence ; transférer en partie (étude d'assurance) | F5: DBUC04, seul scénario de niveau 4, est le volet confidentialité du risque : exfiltration de données avant chiffrement (double extorsion). Son niveau vient de l'exposition naturelle standard 4 aux logiciels malveillants. Le blocage des postes et l'effacement de fichiers (SAPD24, DBUD03) sont de niveau 3. Le guide demande des mesures d'urgence hors cycle budgétaire (p.16). | G5: Un logiciel malveillant introduit par une pièce jointe, un lien ou un support exfiltre des fichiers, puis les chiffre ou les efface et rend les postes inutilisables. | H5: DBUC04, DBUD03, SAPD24 | I5: =_xlfn.MAXIFS('Scénarios retenus'!$N$5:$N$24,'Scénarios retenus'!$B$5:$B$24,$A5) -> 4 | J5: =_xlfn.MAXIFS('Scénarios retenus'!$Q$5:$Q$24,'Scénarios retenus'!$B$5:$B$24,$A5) -> 3 | K5: =_xlfn.MAXIFS('Scénarios retenus'!$R$5:$R$24,'Scénarios retenus'!$B$5:$B$24,$A5) -> 2 | L5: 4A02 = 0,92 (antivirus actif mais non piloté, H-16) ; 6B01 = 0 (disques non chiffrés) ; 4A03 = 0,8 (sauvegardes sans contrôle ni copie hors site, H-19) | M5: PMAL, CHDB, SADC | N5: A03, A04, A05, A09, A13, A14, A17 | O5: Transfert : étude d'une assurance cyber (A17). Les sauvegardes (SADC) n'abaissent pas la gravité calculée de DBUC04 mais conditionnent la reprise après infection ; la réponse à incident (A14) encadre la notification à la CNIL. | P5: — | Q5: Direction
A6: RP-2 | B6: Comptes des salariés, des formateurs et des administrateurs ; outils internes joints par le VPN ; fichiers bureautiques | C6: Usurpation de comptes et divulgation après hameçonnage | D6: ="Actuel "&I6&" ; après plan "&J6&" ; à terme "&K6 -> Actuel 3 ; après plan 3 ; à terme 2 | E6: Réduire | F6: Incident déjà subi (énoncé p.2) ; R-01 (§7 p.5) : MFA, sensibilisation ciblée, revue des privilèges, supervision. Couvre l'accès distant par le VPN avec un compte volé (H-05). L'usage d'un compte volé sur les services cloud est traité avec DEXC01 (RP-5). | G6: Un salarié ou un formateur répond à un message d'hameçonnage : il transmet des fichiers ou ses identifiants ; un tiers se connecte avec ce compte, y compris par le VPN, puis consulte, télécharge ou modifie des données. | H6: DBUC03, DAPC01-b, DAPI01-a | I6: =_xlfn.MAXIFS('Scénarios retenus'!$N$5:$N$24,'Scénarios retenus'!$B$5:$B$24,$A6) -> 3 | J6: =_xlfn.MAXIFS('Scénarios retenus'!$Q$5:$Q$24,'Scénarios retenus'!$B$5:$B$24,$A6) -> 3 | K6: =_xlfn.MAXIFS('Scénarios retenus'!$R$5:$R$24,'Scénarios retenus'!$B$5:$B$24,$A6) -> 2 | L6: 1C06 = 0 (aucune procédure ni formation, H-23) ; 3A07 = 0 (pas d'authentification forte, H-01) ; 3A04 = 0,21 (identifiant et mot de passe seulement, H-21) ; 3A09 = 0,8 (MFA disponible mais non imposé, H-17) | M6: PMAL, CASA | N6: A01, A02, A03, A10, A14 | O6: — | P6: R-01 | Q6: Direction
A7: RP-3 | B7: Données des outils internes (serveurs virtuels) et données externalisées sur le cloud (LMS, CRM, facturation, stockage collaboratif) | C7: Perte de données faute de sauvegardes restaurables | D7: ="Actuel "&I7&" ; après plan "&J7&" ; à terme "&K7 -> Actuel 3 ; après plan 2 ; à terme 2 | E7: Réduire | F7: Incident « absence ponctuelle de sauvegardes vérifiées » (énoncé p.2). L'énoncé demande de formaliser et tester une restauration (P1, Mois 2). DAPD02 porte sur les outils internes, sauvegardés avec le NAS (SADC, A05) ; les données SaaS relèvent de DEXD01 (copie indépendante, DIDE, A06). Le résiduel reste à 2 même si les services ne dépassent pas 3. | G7: Des données sont effacées par erreur ; la restauration échoue ou est incomplète car les sauvegardes n'ont pas été vérifiées. | H7: DAPD02, DEXD01 | I7: =_xlfn.MAXIFS('Scénarios retenus'!$N$5:$N$24,'Scénarios retenus'!$B$5:$B$24,$A7) -> 3 | J7: =_xlfn.MAXIFS('Scénarios retenus'!$Q$5:$Q$24,'Scénarios retenus'!$B$5:$B$24,$A7) -> 2 | K7: =_xlfn.MAXIFS('Scénarios retenus'!$R$5:$R$24,'Scénarios retenus'!$B$5:$B$24,$A7) -> 2 | L7: 4A03 = 0,8 (sauvegarde nocturne, plusieurs générations, sans plan de contrôle ni copie hors site, H-19) ; 4A04 = 0 (aucune copie interne des données SaaS, H-02) | M7: SADC, DIDE | N7: A05, A06, A13 | O7: Objectifs de reprise (H-31) : perte de données maximale 24 h ; reprise du NAS et des outils internes en 1 jour ouvré. | P7: Plan de traitement §7 | Q7: Direction administrative et financière
A8: RP-4 | B8: Continuité des formations : LMS, visioconférence, messagerie | C8: Indisponibilité d'un service SaaS critique | D8: ="Actuel "&I8&" ; après plan "&J8&" ; à terme "&K8 -> Actuel 3 ; après plan 2 ; à terme 2 | E8: Réduire ; transfert marginal | F8: Incident d'indisponibilité SaaS subi (énoncé p.2) ; R-03 propose PCA, procédure de contournement, engagements contractuels et tests (§7 p.5). SEXD01 (disparition du prestataire) est regroupé avec SEXD02 : même actif, même gravité, même traitement ; la réversibilité des contrats est traitée par A06. La part transférée dépend des contrats, non fournis (M-10). | G8: Le prestataire d'un service SaaS critique est en panne ou indisponible pendant une session : les formations et les échanges sont interrompus. | H8: SEXD02, CEPD02 (SEXD01 regroupé) | I8: =_xlfn.MAXIFS('Scénarios retenus'!$N$5:$N$24,'Scénarios retenus'!$B$5:$B$24,$A8) -> 3 | J8: =_xlfn.MAXIFS('Scénarios retenus'!$Q$5:$Q$24,'Scénarios retenus'!$B$5:$B$24,$A8) -> 2 | K8: =_xlfn.MAXIFS('Scénarios retenus'!$R$5:$R$24,'Scénarios retenus'!$B$5:$B$24,$A8) -> 2 | L8: 5D02 = 0 (ni service minimal ni solution de repli, H-24) ; 6A03 = 0 (pas de secours de la messagerie) ; 1E03 = 0 ; 1E01 = 0 | M8: PSSE, SMEL | N8: A06, A07, A17 | O8: Transfert marginal : une PME de 45 personnes obtient rarement des engagements de service négociés auprès d'éditeurs SaaS qui appliquent leurs conditions générales, et une assurance cyber couvre rarement une panne du fournisseur qui n'est pas un incident cyber. L'essentiel est la réduction : mode dégradé activé en moins de 4 heures (A07, H-31) et réversibilité des contrats (A06). | P8: R-03 | Q8: Responsable pédagogique
A9: RP-5 | B9: Dossiers apprenants et données RH (fichiers bureautiques, stockage cloud, LMS) ; comptes d'anciens apprenants | C9: Divulgation par erreur de partage de fichiers | D9: ="Actuel "&I9&" ; après plan "&J9&" ; à terme "&K9 -> Actuel 3 ; après plan 3 ; à terme 2 | E9: Réduire | F9: Erreurs de partage subies (énoncé p.2) ; R-02 (§7 p.5) : classification, restriction des partages, revue des droits, journalisation. Couvre aussi les comptes d'anciens apprenants restés actifs dans le LMS (H-22). Limite de la base : MEHARI ne réduit DBUC02 que par le chiffrement sur le poste (6B01) ; l'effet réel des règles de partage (A08) est estimé hors classeur (R-23). | G9: Un fichier est envoyé au mauvais destinataire ou un espace cloud est partagé par un lien trop ouvert ; une personne extérieure accède à des données personnelles. | H9: DBUC02, DEXC01 | I9: =_xlfn.MAXIFS('Scénarios retenus'!$N$5:$N$24,'Scénarios retenus'!$B$5:$B$24,$A9) -> 3 | J9: =_xlfn.MAXIFS('Scénarios retenus'!$Q$5:$Q$24,'Scénarios retenus'!$B$5:$B$24,$A9) -> 3 | K9: =_xlfn.MAXIFS('Scénarios retenus'!$R$5:$R$24,'Scénarios retenus'!$B$5:$B$24,$A9) -> 2 | L9: 6B03 = 0 (aucune règle de partage, H-27) ; 6B01 = 0 ; 3A09 = 0,8 (MFA non imposé, H-17) | M9: CHDB, CASE | N9: A02, A08, A09, A10, A14 | O9: Effet de A08 estimé par l'équipe hors classeur (R-23) : liens publics supprimés et partage externe limité ramènent DBUC02 et DEXC01 à 2 ; MEHARI obtient aussi 2 par CHDB et CASE. | P9: R-02 | Q9: Direction administrative et financière
A10: RP-6 | B10: Données des outils internes et leurs sauvegardes ; comptes administrateurs | C10: Abus de droits par un utilisateur autorisé ou un administrateur | D10: ="Actuel "&I10&" ; après plan "&J10&" ; à terme "&K10 -> Actuel 3 ; après plan 3 ; à terme 3 | E10: Réduire, puis accepter 12 mois (dérogation à la grille) | F10: Droits « variables selon les applications » (énoncé p.2) et comptes génériques (H-21). Après le plan, DAPD03 passe à 2 ; DAPC01-a et DAPI01-b restent à 3, car la base ne les réduit que par la dissuasion (3A08, 4A11). Options examinées : double validation des dossiers de financement et contrôles de vraisemblance (séparation des tâches, 5A03) contre la falsification (DAPI01-b) ; restriction des exports et des téléchargements massifs contre la diffusion (DAPC01-a) ; sauvegardes immuables contre la destruction des données et de leurs sauvegardes (DAPD03, A05). Même avec l'inventaire et le moindre privilège (A01, A10), la gravité reste 3 (H-32) : l'acceptation est une dérogation à la grille, soumise à la direction (A12). | G10: Une personne disposant de droits légitimes, notamment un administrateur, copie, modifie ou détruit des données, y compris les sauvegardes. | H10: DAPC01-a, DAPI01-b, DAPD03 | I10: =_xlfn.MAXIFS('Scénarios retenus'!$N$5:$N$24,'Scénarios retenus'!$B$5:$B$24,$A10) -> 3 | J10: =_xlfn.MAXIFS('Scénarios retenus'!$Q$5:$Q$24,'Scénarios retenus'!$B$5:$B$24,$A10) -> 3 | K10: =_xlfn.MAXIFS('Scénarios retenus'!$R$5:$R$24,'Scénarios retenus'!$B$5:$B$24,$A10) -> 3 | L10: 3A06 = 0 ; 3A07 = 0 ; 3A08 = 0 ; 4A11 = 0 (aucune journalisation revue, H-26) ; H-06, H-21 | M10: SUAI | N10: A01, A10, A11, A12 | O10: Acceptation pour 12 mois de DAPC01-a et DAPI01-b (colonne AA = A), validée par la direction comme dérogation à la grille, si : inventaire des droits fait (A01) ; revue trimestrielle des droits privilégiés (A10) ; journalisation et revue mensuelle des actions privilégiées, prestataire compris (A11) ; réexamen à M6. Sortie : pour DAPI01-b, le projet PIDA (phase 2, mois 7 à 9) et la double validation des dossiers ; pour DAPC01-a, la base MEHARI n'offre aucune sortie (il reste à 3 même avec des cibles à 4) : restriction des exports à étudier hors classeur, puis nouvelle décision à M12. | P10: — | Q10: Direction
A11: RP-7 | B11: Données circulant sur le réseau local ou stockées sur les postes nomades et personnels (portables des salariés, ordinateurs des formateurs extérieurs) | C11: Fuite de données par le réseau local et les postes nomades ou personnels | D11: ="Actuel "&I11&" ; après plan "&J11&" ; à terme "&K11 -> Actuel 3 ; après plan 3 ; à terme 2 | E11: Réduire | F11: Couvre les équipements réseau et l'accès distant du périmètre minimal (énoncé p.2). Réseau non cloisonné et Wi-Fi des apprenants supposé non séparé (H-20) : DBUC05 est conditionnel à cette hypothèse. Formateurs sur ordinateur personnel (H-21) ; données d'apprenants sur les portables (H-28). DBUC10-b est une approximation du vol de portable, absent de la base. | G11: Une personne connectée au Wi-Fi capte des fichiers échangés avec le NAS ; un proche d'un formateur copie des fichiers depuis son ordinateur personnel ; un portable volé expose les données de son disque. | H11: DBUC05, DBUC01-e, DBUC10-b | I11: =_xlfn.MAXIFS('Scénarios retenus'!$N$5:$N$24,'Scénarios retenus'!$B$5:$B$24,$A11) -> 3 | J11: =_xlfn.MAXIFS('Scénarios retenus'!$Q$5:$Q$24,'Scénarios retenus'!$B$5:$B$24,$A11) -> 3 | K11: =_xlfn.MAXIFS('Scénarios retenus'!$R$5:$R$24,'Scénarios retenus'!$B$5:$B$24,$A11) -> 2 | L11: 5B01 = 1 (TLS vers les SaaS, flux internes non chiffrés, H-20) ; 1B05 = 0 ; 6C02 = 0 (H-21) ; 6B01 = 0 ; 2D01 à 2D03 = 0 (H-29) | M11: CHED, SAMP, CHDB | N11: A09, A15, A16 | O11: Si le Wi-Fi des apprenants s'avère séparé (H-20), DBUC05 sort de la sélection. | P11: — | Q11: Direction
A12: RP-8 | B12: Messagerie d'AFN ; échanges avec les financeurs, les entreprises clientes et les apprenants (facturation et encaissement) | C12: Usurpation de l'identité d'AFN par courriel (fraude au RIB) | D12: ="Actuel "&I12&" ; après plan "&J12&" ; à terme "&K12 -> Actuel 3 ; après plan 3 ; à terme 2 | E12: Réduire | F12: Fraude au changement de RIB, fréquente dans les PME ; l'activité « Facturation et encaissement » n'avait aucun scénario. Intégrité de la messagerie cotée 3 (J-11). Le levier est l'authentification du domaine de messagerie (SPF, DKIM, DMARC) et la vérification des changements de RIB par un autre canal, pas la vigilance face à l'hameçonnage (RP-2). | G12: Un fraudeur envoie au nom d'AFN un courriel portant un faux RIB à un financeur ou à une entreprise cliente ; le paiement part sur son compte. | H12: CEPI02 | I12: =_xlfn.MAXIFS('Scénarios retenus'!$N$5:$N$24,'Scénarios retenus'!$B$5:$B$24,$A12) -> 3 | J12: =_xlfn.MAXIFS('Scénarios retenus'!$Q$5:$Q$24,'Scénarios retenus'!$B$5:$B$24,$A12) -> 3 | K12: =_xlfn.MAXIFS('Scénarios retenus'!$R$5:$R$24,'Scénarios retenus'!$B$5:$B$24,$A12) -> 2 | L12: 6B03 = 0 (aucune authentification des courriels, aucune règle sur les échanges sensibles, H-30) | M12: SMEL | N12: A18 | O12: — | P12: — | Q12: Direction administrative et financière
A14: Objectif à 6 mois (classeur rendu, services portés au niveau 3) : 13 des 20 scénarios retenus restent au niveau 3 selon la grille actuelle, contre 19 aujourd'hui, et plus aucun n'est de niveau 4 dès la fin du mois 2. Tous les 13 sont en impact 3 et potentialité 2 : avec le critère d'acceptation proposé à la direction (« impact 3 et potentialité 2 : toléré sous surveillance », journal H-34), aucun ne resterait inadmissible. Les scénarios non retenus qui restent au niveau 3 sont listés dans l'onglet « Risques résiduels ».
A15: Trois risques demandent une décision immédiate de la direction : RP-1 (seul niveau 4 : mesures d'urgence A13 dès la semaine 1), RP-2 et RP-3 (incidents déjà subis, actions P1).
A16: Objectif réaliste à 6 mois (services portés au niveau 3, « correctement mis en œuvre ») : 13 des 20 scénarios retenus restent inacceptables, contre 19 aujourd'hui. Si les services atteignent les niveaux cibles du classeur (souvent 4), seuls restent au niveau 3 DAPC01-a et DAPI01-b (RP-6), acceptés par dérogation.

Sheet Risques résiduels
A1: Scénarios encore au niveau 3 après le plan (grille actuelle)
A2: Grille actuelle : le niveau 3 est inadmissible et appelle un plan d'action prioritaire (guide p.16 ; cours). Cet onglet rend explicite tout le risque résiduel, retenu ou non (ISO/IEC 27001 §6.1.3). Gravités : classeur rendu, option 3, cibles à 3. Colonne J : statut avec le critère d'acceptation proposé à la direction (« impact 3 et potentialité 2 : toléré sous surveillance », H-34).
A4: Réf. | B4: Ligne Scénarios | C4: Libellé MEHARI | D4: Statut | E4: Gravité actuelle | F4: Gravité après plan | G4: Pourquoi le niveau 3 demeure | H4: Décision proposée | I4: Réexamen | J4: Avec le critère proposé (H-34)
A5: DAPD03 | B5: 9 | C5: Destruction logique totale (fichiers et leurs sauvegardes) par un membre du personnel doté de droits privilégiés | D5: Retenu (RP-6) | E5: 3 | F5: 3 | G5: Avec des cibles à 3, le plan ne change ni l'impact ni la potentialité (3 et 2) ; l'effet n'apparaît qu'avec des protections matures (gravité à terme : 2). | H5: En cours de réduction par le plan : pas d'acceptation, réévaluation à M6 | I5: M6 | J5: Toléré sous surveillance
A6: DAPI01-a | B6: 26 | C6: Falsification ou altération de données — en exploitation, par une personne non autorisée | D6: Retenu (RP-2) | E6: 3 | F6: 3 | G6: Potentialité ramenée de 3 à 2 par le plan ; l'impact reste 3, et la grille donne 3 pour un impact 3 et une potentialité 2. | H6: En cours de réduction par le plan : pas d'acceptation, réévaluation à M6 | I6: M6 | J6: Toléré sous surveillance
A7: DAPI01-b | B7: 27 | C7: Falsification ou altération de données — lors de traitements utilisateurs, par un utilisateur autorisé (dont le personnel ayant des droits privilégiés) | D7: Retenu (RP-6) | E7: 3 | F7: 3 | G7: La base ne le réduit que par la dissuasion (3A08, 4A11) ; effet estimé de A01 et A10 : potentialité 2, gravité toujours 3 (H-32). | H7: Acceptation 12 mois par dérogation (RP-6), sous conditions A01, A10, A11 ; sortie : PIDA (phase 2) et double validation des dossiers | I7: M6 | J7: Toléré sous surveillance
A8: DAPC01-a | B8: 37 | C8: Téléchargement, duplication ou diffusion volontaire de données — par un utilisateur autorisé (dont le personnel ayant des droits privilégiés) | D8: Retenu (RP-6) | E8: 3 | F8: 3 | G8: La base ne le réduit que par la dissuasion (3A08, 4A11), et il reste à 3 même avec des cibles à 4 ; effet estimé de A01 et A10 : potentialité 2, gravité toujours 3 (H-32). | H8: Acceptation 12 mois par dérogation (RP-6), sous conditions A01, A10, A11 ; pas de sortie dans la base : restriction des exports à étudier, décision à M12 | I8: M6 | J8: Toléré sous surveillance
A9: DAPC01-b | B9: 38 | C9: Téléchargement, duplication ou diffusion volontaire de données — par un tiers non autorisé | D9: Retenu (RP-2) | E9: 3 | F9: 3 | G9: Potentialité ramenée de 3 à 2 par le plan ; l'impact reste 3, et la grille donne 3 pour un impact 3 et une potentialité 2. | H9: En cours de réduction par le plan : pas d'acceptation, réévaluation à M6 | I9: M6 | J9: Toléré sous surveillance
A10: DBUC01-e | B10: 76 | C10: Téléchargement, duplication ou diffusion volontaire de fichiers de données — par un proche d'un utilisateur autorisé, via son appareil personnel déclaré et autorisé | D10: Retenu (RP-7) | E10: 3 | F10: 3 | G10: Potentialité ramenée de 3 à 2 par le plan ; l'impact reste 3, et la grille donne 3 pour un impact 3 et une potentialité 2. | H10: En cours de réduction par le plan : pas d'acceptation, réévaluation à M6 | I10: M6 | J10: Toléré sous surveillance
A11: DBUC02 | B11: 77 | C11: Diffusion accidentelle d'un fichier de données | D11: Retenu (RP-5) | E11: 3 | F11: 3 | G11: Potentialité ramenée de 3 à 2 par le plan ; l'impact reste 3, et la grille donne 3 pour un impact 3 et une potentialité 2. | H11: En cours de réduction par le plan : pas d'acceptation, réévaluation à M6 | I11: M6 | J11: Toléré sous surveillance
A12: DBUC03 | B12: 78 | C12: Diffusion par l'utilisateur de fichiers de données , incluant les fichiers relatifs aux courriels reçus ou émis, agendas et contacts, par abus de confiance (hameçonnage ou "phishing") | D12: Retenu (RP-2) | E12: 3 | F12: 3 | G12: Potentialité ramenée de 3 à 2 par le plan ; l'impact reste 3, et la grille donne 3 pour un impact 3 et une potentialité 2. | H12: En cours de réduction par le plan : pas d'acceptation, réévaluation à M6 | I12: M6 | J12: Toléré sous surveillance
A13: DBUC04 | B13: 79 | C13: Diffusion malveillante de fichiers de données par un logiciel malveillant (y compris rançongiciel et action différée après introduction d'un cheval de Troie) | D13: Retenu (RP-1) | E13: 4 | F13: 3 | G13: Potentialité ramenée de 4 à 2 par le plan ; l'impact reste 3, et la grille donne 3 pour un impact 3 et une potentialité 2. | H13: En cours de réduction par le plan : pas d'acceptation, réévaluation à M6 | I13: M6 | J13: Toléré sous surveillance
A14: DBUC05 | B14: 80 | C14: Captation et divulgation de données en transit | D14: Retenu (RP-7) | E14: 3 | F14: 3 | G14: Avec des cibles à 3, le plan ne change ni l'impact ni la potentialité (3 et 2) ; l'effet n'apparaît qu'avec des protections matures (gravité à terme : 2). | H14: En cours de réduction par le plan : pas d'acceptation, réévaluation à M6 | I14: M6 | J14: Toléré sous surveillance
A15: DBUC10-b | B15: 86 | C15: Vol physique ou duplication — dans les bureaux, par une personne non autorisée (approximation du vol de portable) | D15: Retenu (RP-7) | E15: 3 | F15: 3 | G15: Potentialité ramenée de 3 à 2 par le plan ; l'impact reste 3, et la grille donne 3 pour un impact 3 et une potentialité 2. | H15: En cours de réduction par le plan : pas d'acceptation, réévaluation à M6 | I15: M6 | J15: Toléré sous surveillance
A16: CEPI02 | B16: 110 | C16: Émission de faux courriel | D16: Retenu (RP-8) | E16: 3 | F16: 3 | G16: Potentialité ramenée de 3 à 2 par le plan ; l'impact reste 3, et la grille donne 3 pour un impact 3 et une potentialité 2. | H16: En cours de réduction par le plan : pas d'acceptation, réévaluation à M6 | I16: M6 | J16: Toléré sous surveillance
... A55: DBUC10-c | B55: 87 | C55: Vol physique ou duplication — lors de la mise au rebut d'un media | D55: Non évalué (itération 1) | E55: 3 | F55: 3 | G55: Événement physique ou environnemental : locaux non décrits dans l'énoncé, questionnaire 2 Phy non audité ; à traiter dans une itération ultérieure | H55: La direction prend acte d'une limite de périmètre (pas d'acceptation) ; évaluation à M6 avec le diagnostic étendu | I55: M6 | J55: Toléré sous surveillance
A57: 51 scénarios restent au niveau 3 après le plan : 13 retenus (11 en cours de réduction, 2 acceptés de RP-6) et 38 non retenus, dont 3 hors périmètre et 35 non évalués dans cette itération. Aucun n'est de niveau 4. Avec le critère proposé, les 13 retenus et 14 des non retenus seraient tolérés sous surveillance ; les 24 autres (impact 3, potentialité 3) restent à évaluer en priorité à M6.

Sheet Feuille de route
A1: Feuille de route — plan de traitement (modèle §7, p.5–6) et tableau de pilotage
A2: Chaque action est reliée à des risques, des scénarios, des services MEHARI et des mesures ISO 27002:2022 (étape 27). Planning en mois après validation (M0). 19 actions, 6 lots, 12 projets MEHARI décidés, phase 2 en note.
A3: M0 (validation du plan, hypothèse) | D3: 46328
T4: 1 | U4: 2 | V4: 3 | W4: 4 | X4: 5 | Y4: 6 | Z4: 7 | AA4: 8 | AB4: 9 | AC4: 10 | AD4: 11 | AE4: 12
A5: Réf. | B5: Lot (projet de pilotage) | C5: Action (mesure précise) | D5: Risques concernés | E5: Scénarios | F5: Services MEHARI à améliorer | G5: Projet MEHARI | H5: Responsable | I5: Priorité | J5: Charge / coût (niveau — jours-homme ; coût externe estimé) | K5: Début (mois) | L5: Échéance (mois) | M5: Début indicatif | N5: Échéance indicative | O5: Dépendances / prérequis | P5: Indicateur de réalisation | Q5: Indicateur d'efficacité (réévaluation) | R5: Statut | S5: Source | T5: M1 | U5: M2 | V5: M3 | W5: M4 | X5: M5 | Y5: M6 | Z5: M7 | AA5: M8 | AB5: M9 | AC5: M10 | AD5: M11 | AE5: M12
A6: A01 | B6: L1 Identités et accès | C6: Inventorier les comptes et leurs droits, application par application (LMS, messagerie, stockage cloud, CRM, facturation, NAS, serveurs virtuels) : comptes à privilèges, comptes formateurs, comptes génériques. | D6: RP-2, RP-6 | E6: DAPC01-b, DAPI01-a, DAPC01-a, DAPI01-b, DAPD03 | F6: 3A06 (3A06-01, -05) ; 3A02 (3A02-13) · ISO 27002 : 5.15, 5.16, 5.18 | G6: CASA | H6: Responsable IT | I6: P1 | J6: Faible — 3 j·h ; 0 € | K6: 1 | L6: 1 | M6: =EDATE($D$3,K6-1) -> 46328 | N6: =EDATE($D$3,L6)-1 -> 46357 | O6: Aucune. Prérequis de A02, A10, A11. | P6: Inventaire daté couvrant 100 % des applications du périmètre. | Q6: Nombre de comptes génériques ou sans titulaire identifié (cible : 0 à M3). | R6: À lancer | S6: H-06, M-04 ; énoncé p.2 | T6: =IF(AND(T$4>=$K6,T$4<=$L6),1,"") -> 1 | U6: =IF(AND(U$4>=$K6,U$4<=$L6),1,"") | V6: =IF(AND(V$4>=$K6,V$4<=$L6),1,"") | W6: =IF(AND(W$4>=$K6,W$4<=$L6),1,"") | X6: =IF(AND(X$4>=$K6,X$4<=$L6),1,"") | Y6: =IF(AND(Y$4>=$K6,Y$4<=$L6),1,"") | Z6: =IF(AND(Z$4>=$K6,Z$4<=$L6),1,"") | AA6: =IF(AND(AA$4>=$K6,AA$4<=$L6),1,"") | ... AE6: =IF(AND(AE$4>=$K6,AE$4<=$L6),1,"")
A7: A02 | B7: L1 Identités et accès | C7: Activer l'authentification multifacteur (MFA) pour les comptes à privilèges et les accès distants, VPN compris (M1), puis pour tous les comptes des services cloud, formateurs compris (M2). | D7: RP-2, RP-5 | E7: DAPC01-b, DAPI01-a, DEXC01 | F7: 3A07 (3A07-01) ; 3A03 (3A03-01) ; 3A09 (3A09-02) · ISO 27002 : 5.17, 8.5 | G7: CASA, CASE | H7: Responsable IT | I7: P1 | J7: Faible — 3 j·h ; 0 € si les licences SaaS incluent le MFA et l'accès conditionnel (H-09), sinon environ 3 à 6 € par utilisateur et par mois | K7: 1 | L7: 2 | M7: =EDATE($D$3,K7-1) -> 46328 | N7: =EDATE($D$3,L7)-1 -> 46388 | O7: A01. Coût faible si le MFA est inclus dans les abonnements SaaS (hypothèse à vérifier, M-01). | P7: 100 % des comptes concernés enrôlés. | Q7: 3A07 ≥ 3 à la réévaluation M6. | R7: À lancer | S7: Énoncé §7 (MFA, P1, Mois 1) ; H-01 | T7: =IF(AND(T$4>=$K7,T$4<=$L7),1,"") -> 1 | U7: =IF(AND(U$4>=$K7,U$4<=$L7),1,"") -> 1 | V7: =IF(AND(V$4>=$K7,V$4<=$L7),1,"") | W7: =IF(AND(W$4>=$K7,W$4<=$L7),1,"") | X7: =IF(AND(X$4>=$K7,X$4<=$L7),1,"") | Y7: =IF(AND(Y$4>=$K7,Y$4<=$L7),1,"") | Z7: =IF(AND(Z$4>=$K7,Z$4<=$L7),1,"") | AA7: =IF(AND(AA$4>=$K7,AA$4<=$L7),1,"") | ... AE7: =IF(AND(AE$4>=$K7,AE$4<=$L7),1,"")
A8: A03 | B8: L2 Postes, messagerie et réseau | C8: Écrire une procédure anti-hameçonnage (signalement des messages suspects, escalade obligatoire en cas de doute), désigner un point de collecte des messages signalés, sensibiliser 100 % des salariés et formateurs puis faire des rappels réguliers. | D8: RP-2, RP-1 | E8: DBUC03, DBUC04, DBUD03, SAPD24 | F8: 1C06 (1C06-01, -03, -04, -05) ; 6B03 (6B03-08) ; 1C03 (sensibilisation) · ISO 27002 : 6.3, 6.8 | G8: PMAL, SMEL | H8: Direction (pilotage) ; Responsable IT (contenu) | I8: P1 | J8: Faible — 3 j·h ; 0 à 1 k€ (campagne simulée) | K8: 1 | L8: 2 | M8: =EDATE($D$3,K8-1) -> 46328 | N8: =EDATE($D$3,L8)-1 -> 46388 | O8: Aucune. | P8: Procédure diffusée ; part du personnel sensibilisé (cible 100 %). | Q8: 1C06 ≥ 3 à M6 ; taux de clic lors d'une campagne d'hameçonnage simulée (cible inférieure à 10 % à M6) ; nombre de messages suspects signalés. | R8: À lancer | S8: Énoncé p.2 et §7 (sensibilisation ciblée) | T8: =IF(AND(T$4>=$K8,T$4<=$L8),1,"") -> 1 | U8: =IF(AND(U$4>=$K8,U$4<=$L8),1,"") -> 1 | V8: =IF(AND(V$4>=$K8,V$4<=$L8),1,"") | W8: =IF(AND(W$4>=$K8,W$4<=$L8),1,"") | X8: =IF(AND(X$4>=$K8,X$4<=$L8),1,"") | Y8: =IF(AND(Y$4>=$K8,Y$4<=$L8),1,"") | Z8: =IF(AND(Z$4>=$K8,Z$4<=$L8),1,"") | AA8: =IF(AND(AA$4>=$K8,AA$4<=$L8),1,"") | ... AE8: =IF(AND(AE$4>=$K8,AE$4<=$L8),1,"")
A9: A04 | B9: L2 Postes, messagerie et réseau | C9: Vérifier ou déployer une protection anti-malware à jour sur tous les postes, le NAS et les serveurs virtuels ; appliquer systématiquement les correctifs de sécurité ; définir les actions à mener en cas d'infection. | D9: RP-1 | E9: DBUC04, DBUD03, SAPD24 | F9: 4A02 (4A02-01, -03, -04, -05) ; 4A06 (vulnérabilités, correctifs) · ISO 27002 : 8.7, 8.8 | G9: PMAL | H9: Responsable IT / Exploitation | I9: P1 | J9: Moyen — 5 j·h prestataire (≈ 3,5 k€) ; 0 à 1,5 k€/an (console antivirus) | K9: 1 | L9: 2 | M9: =EDATE($D$3,K9-1) -> 46328 | N9: =EDATE($D$3,L9)-1 -> 46388 | O9: A13 (vérification d'urgence) ; inventaire des postes (M-11). | P9: Part des équipements protégés et à jour (cible 100 %). | Q9: 4A02 ≥ 3 à M6 ; DBUC04 ≤ 2 dans le classeur réévalué. | R9: À lancer | S9: Guide p.16 (niveau 4 : mesures d'urgence) | T9: =IF(AND(T$4>=$K9,T$4<=$L9),1,"") -> 1 | U9: =IF(AND(U$4>=$K9,U$4<=$L9),1,"") -> 1 | V9: =IF(AND(V$4>=$K9,V$4<=$L9),1,"") | W9: =IF(AND(W$4>=$K9,W$4<=$L9),1,"") | X9: =IF(AND(X$4>=$K9,X$4<=$L9),1,"") | Y9: =IF(AND(Y$4>=$K9,Y$4<=$L9),1,"") | Z9: =IF(AND(Z$4>=$K9,Z$4<=$L9),1,"") | AA9: =IF(AND(AA$4>=$K9,AA$4<=$L9),1,"") | ... AE9: =IF(AND(AE$4>=$K9,AE$4<=$L9),1,"")
A10: A05 | B10: L3 Sauvegarde et reprise | C10: Formaliser le plan de sauvegarde (données, configurations, postes, copie hors site et hors ligne), réaliser un test de restauration documenté, puis un test par trimestre. | D10: RP-3, RP-1 | E10: DAPD02, DBUD03, SAPD24 | F10: 4A03 (4A03-02, -09, -11, -14, -15) ; 6B04 ; 6B07 · ISO 27002 : 8.13 | G10: SADC | H10: Exploitation | I10: P1 | J10: Moyen — 5 j·h prestataire (≈ 3,5 k€) ; 0,5 à 1,5 k€ (supports, stockage hors site) | K10: 1 | L10: 2 | M10: =EDATE($D$3,K10-1) -> 46328 | N10: =EDATE($D$3,L10)-1 -> 46388 | O10: Politique actuelle de sauvegarde (M-05) ; durée d'interruption tolérable (M-07). | P10: Plan écrit ; test de restauration documenté ; objectifs de reprise atteints : perte de données de 24 h au plus, NAS et outils internes restaurés en 1 jour ouvré (H-31). | Q10: 4A03 ≥ 3 à M6 ; un test réussi par trimestre ; durée réelle de restauration mesurée et comparée à l'objectif (H-31). | R10: À lancer | S10: Énoncé §7 (test de restauration, P1, Mois 2) ; H-02 | T10: =IF(AND(T$4>=$K10,T$4<=$L10),1,"") -> 1 | U10: =IF(AND(U$4>=$K10,U$4<=$L10),1,"") -> 1 | V10: =IF(AND(V$4>=$K10,V$4<=$L10),1,"") | W10: =IF(AND(W$4>=$K10,W$4<=$L10),1,"") | X10: =IF(AND(X$4>=$K10,X$4<=$L10),1,"") | Y10: =IF(AND(Y$4>=$K10,Y$4<=$L10),1,"") | Z10: =IF(AND(Z$4>=$K10,Z$4<=$L10),1,"") | AA10: =IF(AND(AA$4>=$K10,AA$4<=$L10),1,"") | ... AE10: =IF(AND(AE$4>=$K10,AE$4<=$L10),1,"")
A11: A06 | B11: L3 Sauvegarde et reprise | C11: Mettre en place une copie quotidienne des données cloud (LMS, CRM, facturation, stockage collaboratif) indépendante du prestataire, avec tests de relecture trimestriels ; vérifier les clauses de réversibilité et de format des contrats, y compris en cas de disparition du prestataire (SEXD01). | D11: RP-3, RP-4 | E11: DEXD01 | F11: 4A04 (4A04-02, -03, -05, -09) ; 3C01 ; 1F01 à 1F04 (fournisseurs, contrats) · ISO 27002 : 8.13, 5.23 | G11: DIDE | H11: Exploitation (copie) ; Direction (contrats) | I11: P2 | J11: Moyen — 3 j·h prestataire (≈ 2,1 k€) ; 1 à 3 k€/an (outil de sauvegarde SaaS) | K11: 2 | L11: 4 | M11: =EDATE($D$3,K11-1) -> 46358 | N11: =EDATE($D$3,L11)-1 -> 46447 | O11: Liste des services cloud (M-01) ; contrats (M-10). | P11: Copie indépendante quotidienne pour 100 % des services cloud identifiés (perte de données de 24 h au plus, H-31) ; contrats relus. | Q11: 4A04 ≥ 3 à M6. | R11: À lancer | S11: H-02 ; M-10 | T11: =IF(AND(T$4>=$K11,T$4<=$L11),1,"") | U11: =IF(AND(U$4>=$K11,U$4<=$L11),1,"") -> 1 | V11: =IF(AND(V$4>=$K11,V$4<=$L11),1,"") -> 1 | W11: =IF(AND(W$4>=$K11,W$4<=$L11),1,"") -> 1 | X11: =IF(AND(X$4>=$K11,X$4<=$L11),1,"") | Y11: =IF(AND(Y$4>=$K11,Y$4<=$L11),1,"") | Z11: =IF(AND(Z$4>=$K11,Z$4<=$L11),1,"") | AA11: =IF(AND(AA$4>=$K11,AA$4<=$L11),1,"") | ... AE11: =IF(AND(AE$4>=$K11,AE$4<=$L11),1,"")
A12: A07 | B12: L4 Services cloud | C12: Pour le LMS, la visioconférence et la messagerie : analyser la criticité et la durée d'interruption tolérable, écrire une procédure de contournement (mode dégradé), relever les engagements de service des contrats, tester une fois par an. | D12: RP-4 | E12: SEXD02 (SEXD01 regroupé), CEPD02 | F12: 5D02 (5D02-01 à -06) ; 4C04 ; 6A03 · ISO 27002 : 5.23, 5.30 | G12: PSSE, SMEL | H12: Direction ; Responsable IT | I12: P2 | J12: Moyen — 5 j·h ; 0 € | K12: 3 | L12: 4 | M12: =EDATE($D$3,K12-1) -> 46389 | N12: =EDATE($D$3,L12)-1 -> 46447 | O12: M-07 ; M-10 ; A06 pour la récupération des données (5D02-04). | P12: Procédure de contournement documentée et testée pour chaque service critique ; mode dégradé activé en moins de 4 heures (H-31). | Q12: 5D02 ≥ 3 à M6. | R12: À lancer | S12: Énoncé §7, R-03 (PCA, contournement, engagements contractuels, tests) | T12: =IF(AND(T$4>=$K12,T$4<=$L12),1,"") | U12: =IF(AND(U$4>=$K12,U$4<=$L12),1,"") | V12: =IF(AND(V$4>=$K12,V$4<=$L12),1,"") -> 1 | W12: =IF(AND(W$4>=$K12,W$4<=$L12),1,"") -> 1 | X12: =IF(AND(X$4>=$K12,X$4<=$L12),1,"") | Y12: =IF(AND(Y$4>=$K12,Y$4<=$L12),1,"") | Z12: =IF(AND(Z$4>=$K12,Z$4<=$L12),1,"") | AA12: =IF(AND(AA$4>=$K12,AA$4<=$L12),1,"") | ... AE12: =IF(AND(AE$4>=$K12,AE$4<=$L12),1,"")
A13: A08 | B13: L4 Services cloud | C13: Revoir les règles de partage des espaces collaboratifs : liens publics désactivés par défaut, partage externe limité aux cas justifiés, revue trimestrielle des partages. | D13: RP-5 | E13: DEXC01 | F13: 6B03 (6B03-04) · ISO 27002 : 5.10, 5.14 | G13: — (non modélisé, R-23) | H13: Référent SSI ; Responsable IT | I13: P2 | J13: Faible — 2 j·h ; 0 € | K13: 2 | L13: 2 | M13: =EDATE($D$3,K13-1) -> 46358 | N13: =EDATE($D$3,L13)-1 -> 46388 | O13: Classification des données (T1, faite). | P13: Aucun lien public non justifié ; revue trimestrielle. | Q13: Nombre de liens publics actifs non justifiés (cible 0) ; effet estimé hors classeur : DEXC01 et DBUC02 à 2 (R-23). | R13: À lancer | S13: Énoncé §7 (règles de partage, P2, Mois 2) ; H-27, O-15 | T13: =IF(AND(T$4>=$K13,T$4<=$L13),1,"") | U13: =IF(AND(U$4>=$K13,U$4<=$L13),1,"") -> 1 | V13: =IF(AND(V$4>=$K13,V$4<=$L13),1,"") | W13: =IF(AND(W$4>=$K13,W$4<=$L13),1,"") | X13: =IF(AND(X$4>=$K13,X$4<=$L13),1,"") | Y13: =IF(AND(Y$4>=$K13,Y$4<=$L13),1,"") | Z13: =IF(AND(Z$4>=$K13,Z$4<=$L13),1,"") | AA13: =IF(AND(AA$4>=$K13,AA$4<=$L13),1,"") | ... AE13: =IF(AND(AE$4>=$K13,AE$4<=$L13),1,"")
A14: A09 | B14: L2 Postes, messagerie et réseau | C14: Chiffrer les disques des postes portables avec le chiffrement intégré au système, et les pièces jointes contenant des données sensibles. | D14: RP-7, RP-1, RP-5 | E14: DBUC10-b (vol ou perte de portable) ; DBUC04, DBUC02 (formules MEHARI) | F14: 6B01 (6B01-01, -05) · ISO 27002 : 8.1, 8.24 | G14: CHDB | H14: Responsable IT | I14: P2 | J14: Faible — 3 j·h ; 0 € (chiffrement intégré) | K14: 2 | L14: 3 | M14: =EDATE($D$3,K14-1) -> 46358 | N14: =EDATE($D$3,L14)-1 -> 46419 | O14: Inventaire des postes (M-11). | P14: Part des postes portables chiffrés (cible 100 %). | Q14: 6B01 ≥ 3 à la réévaluation. | R14: À lancer | S14: H-28 (formule de prévention de DBUC10-b) ; H-08 (coût faible : outil déjà en place) | T14: =IF(AND(T$4>=$K14,T$4<=$L14),1,"") | U14: =IF(AND(U$4>=$K14,U$4<=$L14),1,"") -> 1 | V14: =IF(AND(V$4>=$K14,V$4<=$L14),1,"") -> 1 | W14: =IF(AND(W$4>=$K14,W$4<=$L14),1,"") | X14: =IF(AND(X$4>=$K14,X$4<=$L14),1,"") | Y14: =IF(AND(Y$4>=$K14,Y$4<=$L14),1,"") | Z14: =IF(AND(Z$4>=$K14,Z$4<=$L14),1,"") | AA14: =IF(AND(AA$4>=$K14,AA$4<=$L14),1,"") | ... AE14: =IF(AND(AE$4>=$K14,AE$4<=$L14),1,"")
A15: A10 | B15: L1 Identités et accès | C15: Adopter une politique de gestion des accès et des départs : attribution nominative validée, retrait des droits au départ ou au changement de poste, désactivation des comptes apprenants à la fin de chaque formation, revue trimestrielle des droits privilégiés et annuelle des autres droits. | D15: RP-6, RP-2, RP-5 | E15: DAPC01-a, DAPI01-b, DAPC01-b, DEXC01 | F15: 3A02 (3A02-06, -07, -11, -14) ; 3A06 (3A06-09, -11) ; 1C05 (cessation de fonction) · ISO 27002 : 5.15, 5.18 | G15: CASA | H15: Direction / RH / IT | I15: P2 | J15: Faible — 3 j·h ; 0 € | K15: 2 | L15: 3 | M15: =EDATE($D$3,K15-1) -> 46358 | N15: =EDATE($D$3,L15)-1 -> 46419 | O15: A01. | P15: Processus validé et contrôles d'échantillon conformes. | Q15: Aucun compte actif d'une personne partie ; aucun compte apprenant actif après la fin de sa session ; 3A02 et 3A06 ≥ 3 à M6. | R15: À lancer | S15: Énoncé §7 (politique d'accès et départs, P2, Mois 3) ; H-21, H-22 | T15: =IF(AND(T$4>=$K15,T$4<=$L15),1,"") | U15: =IF(AND(U$4>=$K15,U$4<=$L15),1,"") -> 1 | V15: =IF(AND(V$4>=$K15,V$4<=$L15),1,"") -> 1 | W15: =IF(AND(W$4>=$K15,W$4<=$L15),1,"") | X15: =IF(AND(X$4>=$K15,X$4<=$L15),1,"") | Y15: =IF(AND(Y$4>=$K15,Y$4<=$L15),1,"") | Z15: =IF(AND(Z$4>=$K15,Z$4<=$L15),1,"") | AA15: =IF(AND(AA$4>=$K15,AA$4<=$L15),1,"") | ... AE15: =IF(AND(AE$4>=$K15,AE$4<=$L15),1,"")
A16: A11 | B16: L1 Identités et accès | C16: Journaliser les actions faites avec des droits privilégiés (consoles d'administration SaaS, NAS, serveurs virtuels), y compris celles du prestataire d'exploitation, conserver les journaux et en présenter une synthèse mensuelle à la hiérarchie. | D16: RP-6 | E16: DAPC01-a, DAPI01-b, DAPD03 | F16: 3A08 (3A08-02, -03, -05) ; 4A11 · ISO 27002 : 8.2, 8.15, 8.16 | G16: SUAI | H16: Responsable IT (mise en place) ; Direction (revue) | I16: P2 | J16: Moyen — 5 j·h ; 0 à 1 k€/an (stockage des journaux) | K16: 3 | L16: 6 | M16: =EDATE($D$3,K16-1) -> 46389 | N16: =EDATE($D$3,L16)-1 -> 46508 | O16: A01. | P16: Journaux actifs pour 100 % des comptes privilégiés inventoriés ; revue mensuelle tracée. | Q16: 3A08 ≥ 3 à M6. | R16: À lancer | S16: Condition de l'acceptation temporaire de RP-6 | T16: =IF(AND(T$4>=$K16,T$4<=$L16),1,"") | U16: =IF(AND(U$4>=$K16,U$4<=$L16),1,"") | V16: =IF(AND(V$4>=$K16,V$4<=$L16),1,"") -> 1 | W16: =IF(AND(W$4>=$K16,W$4<=$L16),1,"") -> 1 | X16: =IF(AND(X$4>=$K16,X$4<=$L16),1,"") -> 1 | Y16: =IF(AND(Y$4>=$K16,Y$4<=$L16),1,"") -> 1 | Z16: =IF(AND(Z$4>=$K16,Z$4<=$L16),1,"") | AA16: =IF(AND(AA$4>=$K16,AA$4<=$L16),1,"") | ... AE16: =IF(AND(AE$4>=$K16,AE$4<=$L16),1,"")
A17: A12 | B17: L5 Gouvernance SSI | C17: Désigner un référent SSI, qui porte aussi la conformité ; faire valider par la direction la grille d'acceptabilité et le critère proposé (H-34), la dérogation de RP-6 et la prise d'acte des scénarios non évalués ; confirmer les hypothèses du journal ; réévaluer les questionnaires et la gravité à M6, en étendant le diagnostic ; décider la phase 2. | D17: Tous | E17: Les 20 retenus | F17: 1B01 (organisation de la SSI) ; prépare 8A01 · ISO 27002 : 5.2, 5.4 | G17: — | H17: Direction | I17: P1 | J17: Moyen — 15 j·h sur 6 mois (pilotage de 19 actions, validation des hypothèses, réévaluation MEHARI à M6) ; 0 € | K17: 1 | L17: 6 | M17: =EDATE($D$3,K17-1) -> 46328 | N17: =EDATE($D$3,L17)-1 -> 46508 | O17: Aucune. | P17: Décisions formalisées (M1) ; réévaluation faite (M6). | Q17: Scénarios retenus inacceptables : 19 aujourd'hui ; 13 à M6 (objectif, cibles à 3) ; 2 à terme (cibles à 4). | R17: À lancer | S17: M-09, M-12 ; guide p.41 (validation de la grille) ; O-18 | T17: =IF(AND(T$4>=$K17,T$4<=$L17),1,"") -> 1 | U17: =IF(AND(U$4>=$K17,U$4<=$L17),1,"") -> 1 | V17: =IF(AND(V$4>=$K17,V$4<=$L17),1,"") -> 1 | W17: =IF(AND(W$4>=$K17,W$4<=$L17),1,"") -> 1 | X17: =IF(AND(X$4>=$K17,X$4<=$L17),1,"") -> 1 | Y17: =IF(AND(Y$4>=$K17,Y$4<=$L17),1,"") -> 1 | Z17: =IF(AND(Z$4>=$K17,Z$4<=$L17),1,"") | AA17: =IF(AND(AA$4>=$K17,AA$4<=$L17),1,"") | ... AE17: =IF(AND(AE$4>=$K17,AE$4<=$L17),1,"")
... A24: A19 | B24: L5 Gouvernance SSI | C24: Mettre en conformité : tenir le registre des traitements (RGPD, art. 30) ; encadrer les éditeurs SaaS comme sous-traitants (art. 28) et vérifier les transferts hors UE ; fixer des durées de conservation, dont la désactivation et la suppression des comptes d'apprenants sortis (minimisation, H-22) ; relever les obligations des financeurs et de Qualiopi ; vérifier le statut d'AFN au regard de NIS2 (H-35). | D24: Hors RP (PGCE01) | E24: PGCE01 | F24: 8A01 ; 8A02 ; 8A03 · ISO 27002 : 5.31, 5.34, 5.36 | G24: CPEX | H24: Direction ; Référent SSI | I24: P2 | J24: Moyen — 5 j·h ; 0 € | K24: 2 | L24: 4 | M24: =EDATE($D$3,K24-1) -> 46358 | N24: =EDATE($D$3,L24)-1 -> 46447 | O24: A12 (référent SSI) ; contrats des financeurs. | P24: Registre des traitements à jour ; liste des obligations validée par la direction. | Q24: 8A01 ≥ 3 à M6 ; PGCE01 au niveau 1 dans le classeur réévalué. | R24: À lancer | S24: Énoncé p.2, étape 8 (non-conformité) ; RGPD art. 30 ; projet CPEX | T24: =IF(AND(T$4>=$K24,T$4<=$L24),1,"") | U24: =IF(AND(U$4>=$K24,U$4<=$L24),1,"") -> 1 | V24: =IF(AND(V$4>=$K24,V$4<=$L24),1,"") -> 1 | W24: =IF(AND(W$4>=$K24,W$4<=$L24),1,"") -> 1 | X24: =IF(AND(X$4>=$K24,X$4<=$L24),1,"") | Y24: =IF(AND(Y$4>=$K24,Y$4<=$L24),1,"") | Z24: =IF(AND(Z$4>=$K24,Z$4<=$L24),1,"") | AA24: =IF(AND(AA$4>=$K24,AA$4<=$L24),1,"") | ... AE24: =IF(AND(AE$4>=$K24,AE$4<=$L24),1,"")
A26: Lots
C27: L0 Mesures d'urgence | D27: =COUNTIF($B$6:$B$24,C27) -> 1 | E27: actions | F27: Projets MEHARI : PMAL, SADC (vérification d'urgence)
C28: L1 Identités et accès | D28: =COUNTIF($B$6:$B$24,C28) -> 4 | E28: actions | F28: Projets MEHARI : CASA, CASE, SUAI
C29: L2 Postes, messagerie et réseau | D29: =COUNTIF($B$6:$B$24,C29) -> 6 | E29: actions | F29: Projets MEHARI : PMAL, SMEL (6B03), CHDB, CHED, SAMP
C30: L3 Sauvegarde et reprise | D30: =COUNTIF($B$6:$B$24,C30) -> 2 | E30: actions | F30: Projets MEHARI : SADC, DIDE
C31: L4 Services cloud | D31: =COUNTIF($B$6:$B$24,C31) -> 2 | E31: actions | F31: Projets MEHARI : PSSE, SMEL (6A03) ; A08 hors classeur
C32: L5 Gouvernance SSI | D32: =COUNTIF($B$6:$B$24,C32) -> 4 | E32: actions | F32: Projet MEHARI CPEX (A19) ; pilotage, réponse à incident, assurance
A34: Répartition
C35: Priorité P1 | D35: =COUNTIF($I$6:$I$24,"P1") -> 8
C36: Priorité P2 | D36: =COUNTIF($I$6:$I$24,"P2") -> 11
C37: Priorité P3 | D37: =COUNTIF($I$6:$I$24,"P3") -> 0
C38: Charge Faible | D38: =COUNTIF($J$6:$J$24,"Faible*") -> 11
C39: Charge Moyen | D39: =COUNTIF($J$6:$J$24,"Moyen*") -> 8
C40: Charge Élevé | D40: =COUNTIF($J$6:$J$24,"Élevé*") -> 0
C41: Charge totale estimée (j·h) | D41: 74
C42: dont actions P1, mois 1–2 (j·h) | D42: 39
A44: Point de vigilance : 8 actions P1 sur les deux premiers mois, environ 39 jours-homme : 11 pour le prestataire (A04, A05, A13), 15 de pilotage étalés sur six mois (A12) et environ 13 jours-homme internes sur deux mois, soit 1,5 jour par semaine partagé entre le responsable IT à temps partiel et la direction (A03, A14). Total du plan : 74 jours-homme, dont 17 jours de prestataire (≈ 12 k€ à 700 € par jour) et 57 jours internes (≈ 20 k€ à 350 € chargés par jour, coût d'opportunité, H-08). Coût externe estimé la première année : environ 16 à 26 k€, dont 3 à 11 k€ récurrents (abonnements, assurance si souscrite), hors licences MFA si elles ne sont pas incluses. Si une seule personne porte ces rôles, étaler A04 et A05 jusqu'au mois 3, sans décaler A13. Le planning est au mois : A13 occupe les semaines 1 et 2 du mois 1.
A46: Phase 2 (mois 7 à 12, décision et chiffrage à la réévaluation de M6, non budgétée ici) : PIDA, intégrité des données applicatives (mois 7 à 9 ; sortie de l'acceptation de DAPI01-b) ; CHDA, chiffrement des données applicatives (selon les éditeurs) ; PCDE, confidentialité des données externalisées (après A02 et A08) ; SUBU, surveillance des bureaux ; COMA, contrôle des opérations de maintenance du prestataire (DAPC01-c). Les quatre premiers sont ceux que propose Sel_Projets avec des cibles à 3.

Sheet Scénarios retenus
A1: Scénarios retenus (20) — étape 19 : quel actif ? quel événement ou acteur ? quelle conséquence métier ?
A2: Libellés, I/P/G et formules de mesures repris de la feuille Scénarios du classeur. Colonnes E à G : rédaction de l'équipe à partir de T1/T2 et de l'énoncé.
A4: Réf. scénario | B4: Risque prioritaire | C4: Libellé MEHARI (col. G–H) | D4: Type d'actif MEHARI (col. B, D) | E4: Actif ou processus AFN touché | F4: Événement ou acteur | G4: Conséquence métier redoutée | H4: Critère | I4: Impact intrinsèque (L) | J4: Exposition (M) | K4: Gravité intrinsèque (P) | L4: I actuel (X) | M4: P actuelle (Y) | N4: Gravité actuelle (Z) | O4: I après plan (cibles à 3) | P4: P après plan (cibles à 3) | Q4: Gravité après plan (cibles à 3) | R4: Gravité à terme (cibles à 4) | S4: Services de réduction (formules MEHARI, col. AC–AF) | T4: Projets du plan | U4: Décision col. AA | V4: Ligne Scénarios | W4: Lien énoncé / journal
A5: DBUC04 | B5: RP-1 | C5: Diffusion malveillante de fichiers de données par un logiciel malveillant (y compris rançongiciel et action différée après introduction d'un cheval de Troie) | D5: D02 — Fichier ou base de données | E5: Fichiers bureautiques sur le NAS et les postes (T1 domaines 6 et 9, C = 3) | F5: Logiciel malveillant, dont rançongiciel à double extorsion (IF.L.Vir) ; exposition naturelle 4 (valeur standard) | G5: Fuite (exfiltration) de données RH et personnelles par le logiciel malveillant : volet confidentialité de RP-1, seul scénario de niveau 4 | H5: C | I5: 3 | J5: 4 | K5: 4 | L5: 3 | M5: 4 | N5: 4 | O5: 3 | P5: 2 | Q5: 3 | R5: 2 | S5: Prév. : max(4A02,6B01) | T5: PMAL, CHDB | U5: — | V5: 79 | W5: Seul scénario de niveau 4 de la base ; périmètre « postes de travail » (énoncé p.2)
A6: DBUD03 | B6: RP-1 | C6: Effacement de fichiers de données par un virus ou un logiciel malveillant (sur un serveur de données partagées ou sur le poste de travail) | D6: D02 — Fichier ou base de données | E6: Fichiers bureautiques partagés (NAS) et fichiers des postes (D02, D = 2) | F6: Virus ou logiciel malveillant (IF.L.Vir) ; exposition naturelle 4 | G6: Fichiers effacés : travail administratif à reconstituer | H6: D | I6: 2 | J6: 4 | K6: 3 | L6: 2 | M6: 4 | N6: 3 | O6: 2 | P6: 2 | Q6: 2 | R6: 1 | S6: Prév. : 4A02; Pall. : min(4A03,6B04) | T6: PMAL, SADC | U6: — | V6: 50 | W6: Périmètre « postes de travail, sauvegardes » (énoncé p.2)
A7: SAPD24 | B7: RP-1 | C7: Indisponibilité massive d'équipements des utilisateurs, due à un logiciel malveillant (virus, rançongiciel, etc.) | D7: S01 — Environnement de travail et équipement des utilisateurs | E7: Postes de travail des salariés et formateurs (T2 S01, D = 2) | F7: Logiciel malveillant, rançongiciel (IF.L.Vir) ; exposition naturelle 4 | G7: Postes inutilisables : arrêt du travail administratif et des formations dispensées depuis ces postes | H7: D | I7: 2 | J7: 4 | K7: 3 | L7: 2 | M7: 4 | N7: 3 | O7: 2 | P7: 2 | Q7: 2 | R7: 1 | S7: Prév. : 4A02; Pall. : 6B07 | T7: PMAL, SADC | U7: — | V7: 174 | W7: Périmètre « postes de travail » (énoncé p.2)
A8: DBUC03 | B8: RP-2 | C8: Diffusion par l'utilisateur de fichiers de données , incluant les fichiers relatifs aux courriels reçus ou émis, agendas et contacts, par abus de confiance (hameçonnage ou "phishing") | D8: D02 — Fichier ou base de données | E8: Fichiers bureautiques et courriels (données RH, données personnelles : T1 domaines 6 et 9, C = 3) | F8: Salarié ou formateur trompé par un message d'hameçonnage (AH.L.Phi) | G8: Divulgation de données personnelles d'apprenants ou de salariés | H8: C | I8: 3 | J8: 3 | K8: 3 | L8: 3 | M8: 3 | N8: 3 | O8: 3 | P8: 2 | Q8: 3 | R8: 2 | S8: Prév. : 1C06 | T8: PMAL | U8: — | V8: 78 | W8: Incident d'hameçonnage subi (énoncé p.2) ; R-01 (énoncé p.5)
A9: DAPC01-b | B9: RP-2 | C9: Téléchargement, duplication ou diffusion volontaire de données — par un tiers non autorisé | D9: D01 — Fichier ou base de données | E9: Données des outils internes hébergés sur les serveurs virtuels : dossiers administratifs et de financement, contrats (T1 domaines 2 et 9, C = 3) | F9: Tiers non autorisé (AH.L.Vol) ; interprétation : il se connecte par le VPN avec un compte volé par hameçonnage (H-05) | G9: Exposition de dossiers de financement et de données personnelles d'apprenants | H9: C | I9: 3 | J9: 3 | K9: 3 | L9: 3 | M9: 3 | N9: 3 | O9: 3 | P9: 2 | Q9: 3 | R9: 2 | S9: Prév. : max(min(3A04,3A07),5B02) | T9: CASA | U9: — | V9: 38 | W9: R-01 (énoncé p.5) ; H-01 (MFA non systématique)
A10: DAPI01-a | B10: RP-2 | C10: Falsification ou altération de données — en exploitation, par une personne non autorisée | D10: D01 — Fichier ou base de données | E10: Données des outils internes (serveurs virtuels) : dossiers administratifs et de financement (T1 domaines 2 et 9, I = 3) | F10: Personne non autorisée (AH.L.Fal) ; interprétation : via un compte usurpé, joint par le VPN | G10: Dossiers administratifs ou de financement altérés : erreurs administratives, retard de prise en charge | H10: I | I10: 3 | J10: 3 | K10: 3 | L10: 3 | M10: 3 | N10: 3 | O10: 3 | P10: 2 | Q10: 3 | R10: 2 | S10: Prév. : max(min(3A04,3A07),5A02,5B02); Conf. : 5A03 | T10: CASA | U10: — | V10: 26 | W10: R-01 (énoncé p.5) ; énoncé p.3 (dossiers de financement : I élevée)
A11: DAPD02 | B11: RP-3 | C11: Effacement accidentel de données | D11: D01 — Fichier ou base de données | E11: Données des outils internes (serveurs virtuels) : dossiers administratifs et de financement (T1 domaine 2, D = 3), sauvegardées avec le NAS (H-19) | F11: Erreur de manipulation ou de procédure (ER.P.Pro) | G11: Perte de dossiers administratifs ou de financement ; restauration incertaine | H11: D | I11: 3 | J11: 3 | K11: 3 | L11: 3 | M11: 3 | N11: 3 | O11: 2 | P11: 3 | Q11: 2 | R11: 2 | S11: Pall. : 4A03 | T11: SADC | U11: — | V11: 8 | W11: « Absence ponctuelle de sauvegardes vérifiées » (énoncé p.2)
A12: DEXD01 | B12: RP-3 | C12: Effacement accidentel de fichier de données | D12: D07 — Fichier ou base de données | E12: Données externalisées sur le cloud : LMS, CRM, facturation, stockage collaboratif (T1 domaines 1 à 5, 9, processus 1 et 2, D = 3) | F12: Effacement accidentel (ER.P.Pro) | G12: Perte de contenus de formation, de suivis ou de dossiers stockés chez le prestataire, sans copie indépendante vérifiée | H12: D | I12: 3 | J12: 3 | K12: 3 | L12: 3 | M12: 3 | N12: 3 | O12: 2 | P12: 3 | Q12: 2 | R12: 2 | S12: Pall. : 4A04 | T12: DIDE | U12: — | V12: 135 | W12: H-02 (pas de tests de restauration trimestriels) ; énoncé p.2
A13: SEXD02 | B13: RP-4 | C13: Arrêt de fonctionnement d'un élément de l'infrastructure support des services externalisés | D13: S02 — Infrastructure matérielle et logicielle support de services externalisés | E13: Services externalisés : LMS, visioconférence, messagerie (T2 S02 domaine 3 et processus 1, D = 3) | F13: Panne de l'infrastructure du prestataire (AB.S.Ser) ; inclut l'absence du prestataire (SEXD01, regroupé : même actif, même gravité, même traitement) | G13: Formations en cours interrompues | H13: D | I13: 3 | J13: 3 | K13: 3 | L13: 3 | M13: 3 | N13: 3 | O13: 2 | P13: 3 | Q13: 2 | R13: 2 | S13: Pall. : 5D02 | T13: PSSE | U13: — | V13: 199 | W13: Incident d'indisponibilité SaaS subi (énoncé p.2) ; R-03 (énoncé p.5) ; O-04
A14: CEPD02 | B14: RP-4 | C14: Interruption ou indisponibilité des services de partenaires nécessaires à la messagerie électronique | D14: D04 — Courriel en transit | E14: Messagerie électronique (T1 domaine 3 et processus 1, D = 3) | F14: Indisponibilité des services du partenaire de messagerie (AB.S.Ser) | G14: Échanges avec les apprenants et formateurs bloqués pendant les sessions | H14: D | I14: 3 | J14: 3 | K14: 3 | L14: 3 | M14: 3 | N14: 3 | O14: 2 | P14: 3 | Q14: 2 | R14: 1 | S14: Pall. : 6A03 | T14: SMEL | U14: — | V14: 104 | W14: Messagerie « indispensable pendant les périodes de formation » (énoncé p.2, O-04)
A15: DBUC02 | B15: RP-5 | C15: Diffusion accidentelle d'un fichier de données | D15: D02 — Fichier ou base de données | E15: Fichiers bureautiques : données RH et personnelles (T1 domaines 6 et 9, C = 3) | F15: Erreur de manipulation : envoi ou partage au mauvais destinataire (ER.P.Pro) | G15: Exposition de données personnelles | H15: C | I15: 3 | J15: 3 | K15: 3 | L15: 3 | M15: 3 | N15: 3 | O15: 3 | P15: 2 | Q15: 3 | R15: 2 | S15: Prév. : 6B01 | T15: CHDB | U15: — | V15: 77 | W15: Erreurs de partage de fichiers subies (énoncé p.2) ; R-02 (énoncé p.5) ; effet des règles de partage (A08) estimé hors classeur (R-23)
A16: DEXC01 | B16: RP-5 | C16: Téléchargement, duplication ou diffusion volontaire de fichiers de données | D16: D07 — Fichier ou base de données | E16: Données externalisées sur le cloud : dossiers apprenants, LMS, CRM (T1 domaines 1 à 5, 9, C = 3) | F16: Téléchargement volontaire (AH.L.Vol) ; interprétation : via un lien de partage mal configuré, un compte cloud volé ou le compte d'un ancien apprenant resté actif (H-22) | G16: Divulgation de dossiers apprenants | H16: C | I16: 3 | J16: 3 | K16: 3 | L16: 3 | M16: 3 | N16: 3 | O16: 3 | P16: 2 | Q16: 3 | R16: 2 | S16: Prév. : max(3A09,5G02) | T16: CASE | U16: — | V16: 144 | W16: R-02 « partage cloud mal configuré » (énoncé p.5) ; H-22 (comptes apprenants) ; réduit dans le classeur par le MFA des services cloud (3A09, projet CASE)
... A24: PGCE01 | B24: Hors RP | C24: Non application de procédure adaptée au respect des exigences légales ou contractuelles, par absence de procédures adaptées ou par ignorance de la bonne procédure | D24: P01 — Procédure support des processus | E24: Processus de gestion de la conformité (T2 P01, E = 2 : domaines 1, 2, 5, 6, 9) | F24: Procédure absente ou ignorée (PR.N.Nai) | G24: Non-respect d'une obligation légale ou contractuelle (données personnelles, financements) | H24: E | I24: 2 | J24: 2 | K24: 2 | L24: 2 | M24: 2 | N24: 2 | O24: 2 | P24: 2 | Q24: 2 | R24: 1 | S24: Prév. : 8A01 | T24: CPEX | U24: — | V24: 209 | W24: Dysfonctionnement « non-conformité » (énoncé p.2, étape 8) ; 8A01-05 non démontré
A26: Lecture : « Actuel » = gravité actuelle (option 2) ; « après plan » = gravité résiduelle (option 3) du classeur rendu, avec les 12 projets décidés et leurs niveaux cibles fixés à 3 (« correctement mis en œuvre ») : c'est l'objectif à six mois. « À terme » = même calcul sur une copie, avec les cibles d'origine du modèle, souvent 4 (« mature et documenté ») : horizon de 12 à 18 mois. Classeur AFN_MEHARI_v04_2026-10-20.xlsm. Les scénarios D01 portent sur les outils internes des serveurs virtuels ; les données des services SaaS sont en D07 (journal H-18).

Sheet Projets MEHARI
A1: Projets MEHARI — choix et gain calculé (étapes 23–24 ; guide p.47–48)
A2: Simulation sur copies recalculées du classeur v04 (option gravité résiduelle, cibles à 3). « Projet seul » : projet marqué décidé à partir de l'état actuel. « Si retiré » : plan de 12 projets moins ce projet. Comptages sur les 75 scénarios de niveau ≥ 3 de la base, indicatifs : 118 sous-services non audités restent au niveau 1 par défaut.
A4: Code | B4: Libellé (feuille Projets) | C4: Services : niveau actuel → cible (classeur rendu) | D4: Effet sur les scénarios retenus (projet seul, cibles à 3) : gravité G, potentialité P ou impact I | E4: Scénarios de la base ramenés à ≤ 2 (projet seul) | F4: Scénarios repassant à ≥ 3 si le projet est retiré du plan | G4: Actions | H4: Charge / coût | I4: Décision | J4: Justification
A5: PMAL | B5: Protection contre les malwares et actions malveillantes (hameçonnage) | C5: 1C06 0→3 ; 4A02 1→3 | D5: DBUD03 (G 3→2), DBUC03 (P 3→2), DBUC04 (G 4→3), SAPD24 (G 3→2) | E5: 2 | F5: 2 (DBUD03, SAPD24) | G5: A03, A04, A13 | H5: Moyen | I5: Retenu | J5: Projet qui réduit le plus de scénarios retenus, dont le seul niveau 4 ; répond à l'incident d'hameçonnage.
A6: CASA | B6: Contrôle d'accès aux systèmes et applications | C6: 3A02 0→3 ; 3A04 0→3 ; 3A06 0→3 ; 3A07 0→3 | D6: DAPI01-a (P 3→2), DAPC01-b (P 3→2) | E6: 0 | F6: 0 | G6: A01, A02, A10 | H6: Faible | I6: Retenu | J6: Porte le MFA et la gestion des droits demandés par l'énoncé (§7, P1 Mois 1 et P2 Mois 3). Avec une cible à 3, il fait baisser la potentialité de DAPI01-a et DAPC01-b sans changer leur gravité.
A7: SADC | B7: Sauvegardes des données et configurations (non externalisées) | C7: 4A03 1→3 ; 6B04 2→3 ; 6B06 1→3 ; 6B07 0→3 | D7: DAPD02 (G 3→2) | E7: 13 | F7: 13 (DAPD02) | G7: A05, A13 | H7: Moyen | I7: Retenu | J7: Projet le plus efficace sur la base complète (13 scénarios de niveau ≥ 3 ramenés à ≤ 2) ; répond à l'incident « sauvegardes non vérifiées ».
A8: DIDE | B8: Disponibilité des données externalisées | C8: 3C01 1→3 ; 4A04 0→3 | D8: DEXD01 (G 3→2) | E8: 3 | F8: 3 (DEXD01) | G8: A06 | H8: Moyen | I8: Retenu | J8: Seul levier sur la perte de données cloud (4A04) ; H-02.
A9: PSSE | B9: Plans de secours des systèmes externalisés | C9: 4C04 1→3 ; 5D02 0→3 | D9: SEXD02 (G 3→2) | E9: 2 | F9: 2 (SEXD02) | G9: A07 | H9: Moyen | I9: Retenu | J9: Répond à l'incident d'indisponibilité SaaS et à R-03.
A10: CASE | B10: Contrôle d'accès aux systèmes et services externalisés | C10: 3A09 1→3 | D10: DEXC01 (P 3→2) | E10: 0 | F10: 0 | G10: A02 | H10: Faible | I10: Retenu | J10: Porte le MFA des services cloud (3A09-02, action A02) ; réduit DEXC01. Les règles de partage (A08) ne relèvent pas de 3A09 (O-15).
A11: SUAI | B11: Surveillance des activités internes | C11: 3A08 0→3 ; 4A11 0→3 | D11: DAPI01-b (P 3→2), DAPC01-a (P 3→2) | E11: 0 | F11: 2 | G11: A11 | H11: Moyen | I11: Retenu | J11: Condition de l'acceptation temporaire de RP-6 (surveillance des comptes privilégiés, prestataire compris) ; fait baisser la potentialité de DAPC01-a et DAPI01-b.
A12: SMEL | B12: Sécurité des mails et des messages électroniques | C12: 6A03 0→3 ; 6B03 0→3 | D12: CEPD02 (G 3→2), CEPI02 (P 3→2) | E12: 2 | F12: 2 (CEPD02) | G12: A03, A07, A18 | H12: Faible à moyen | I12: Retenu | J12: Continuité de la messagerie (6A03, CEPD02) et sécurité des courriels (6B03) : authentification du domaine contre la fraude au RIB (CEPI02, RP-8) et traitement des messages suspects.
A13: CHDB | B13: Chiffrement des données bureautiques | C13: 6B01 0→3 | D13: DBUC02 (P 3→2), DBUC04 (G 4→3), DBUC10-b (P 3→2) | E13: 0 | F13: 1 | G13: A09 | H13: Faible | I13: Retenu | J13: Chiffrement des disques des portables : seul levier sur DBUC10-b (H-28) ; second levier sur DBUC04 (avec PMAL). Coût faible, mois 2 à 3.
A14: SAMP | B14: Sécurité des appareils mobiles personnels | C14: 6C02 0→3 | D14: DBUC01-e (P 3→2) | E14: 0 | F14: 0 | G14: A16 | H14: Faible | I14: Retenu | J14: Seul projet qui réduit DBUC01-e (ordinateurs personnels des formateurs).
A15: CHED | B15: Chiffrement des échanges de données | C15: 5B01 1→3 | D15: Aucun effet calculé avec une cible à 3 ; avec une cible à 4 : DBUC05 (G 3→2) | E15: 0 | F15: 1 | G15: A15 | H15: Faible | I15: Retenu | J15: Seul projet qui agit sur DBUC05 (captation de fichiers sur le réseau local, conditionnel à H-20). Avec une cible à 3, la gravité calculée ne change pas : l'effet n'apparaît qu'avec une cible à 4. Maintenu parce que le réseau fait partie du périmètre minimal.
A16: CPEX | B16: Conformité aux exigences légales ou contractuelles | C16: 8A01 0→3 ; 8A02 1→3 ; 8A03 1→3 | D16: Aucun effet calculé avec une cible à 3 ; avec une cible à 4 : PGCE01 (G 2→1) | E16: 0 | F16: 0 | G16: A19 | H16: Moyen | I16: Retenu | J16: Décidé : PGCE01 (non-conformité légale) ne peut pas être accepté. Avec une cible à 3, la gravité calculée reste 2 ; avec une cible à 4, PGCE01 passe à 1.
A17: PIDA | B17: Protection de l'intégrité des fichiers de données applicatives | C17: 5A02 0→4 | D17: DAPI01-a (G 3→2), DAPI01-b (G 3→2) | E17: 5 | F17: — | G17: — | H17: — | I17: Phase 2 (M7–M9) | J17: Proposé par Sel_Projets. Réduirait DAPI01-b (RP-6) : c'est la sortie prévue de l'acceptation temporaire ; dépend de l'éditeur des outils (M-01).
A18: CHDA | B18: Chiffrement des données applicatives stockées | C18: 5B02 0→4 | D18: DAPI01-a (G 3→2), DAPC01-b (G 3→2) | E18: 8 | F18: — | G18: — | H18: — | I18: Phase 2 | J18: Proposé par Sel_Projets (DAPI01-a, DAPC01-b). Dépend des fonctions de chiffrement des éditeurs et des outils internes (M-01).
A19: PCDE | B19: Protection de la confidentialité des fichiers de données externalisées | C19: 5G02 0→4 | D19: DEXC01 (G 3→2) | E19: 1 | F19: — | G19: — | H19: — | I19: Phase 2 | J19: Proposé par Sel_Projets (DEXC01). À juger après le MFA (A02) et les règles de partage (A08), qui traitent déjà la cause.
A20: SUBU | B20: Surveillance des zones de bureaux sensbles | C20: 2D03 0→3 | D20: DBUC10-b (P 3→2) | E20: 0 | F20: — | G20: — | H20: — | I20: Phase 2 | J20: Proposé par Sel_Projets (DBUC10-b). Sécurité physique des bureaux, hors de la priorité du plan à six mois.
A21: COMA | B21: Contrôle des opérations de maintenance | C21: 4A09 1→4 ; 7B09 1→4 | D21: DAPC01-c, non retenu (G 3→2) | E21: 5 | F21: — | G21: — | H21: — | I21: Phase 2 | J21: Contrôle des opérations de maintenance (4A09) : seul levier sur DAPC01-c (fuite lors d'une maintenance par le prestataire, H-26), aujourd'hui résiduel hors sélection.
A22: PCAC | B22: Plan de continuité de l'activité | C22: 1E01 0→3 | D22: aucun | E22: 0 | F22: — | G22: — | H22: — | I22: Non retenu (après A07) | J22: Aucun gain calculé ; le PCA global sera bâti sur les plans de secours SaaS (A07).
A23: GPES | B23: Gestion du personnel stratégique | C23: 1E03 0→3 | D23: aucun | E23: 1 | F23: — | G23: — | H23: — | I23: Non retenu | J23: SEXD01 (regroupé avec SEXD02) est déjà ramené à 2 par PSSE.
A25: Sel_Projets, relancée avec les 12 projets décidés et les cibles à 3, propose CHDA, SUBU, PCDE et PIDA : aucun n'est décidé, ils sont reportés en phase 2 avec COMA (journal H-33).

Sheet Synthèse
A1: Synthèse chiffrée
A2: Bloc 1 calculé à partir de l'onglet Scénarios retenus. Blocs 2 et 3 : valeurs relevées dans le classeur (feuilles Scénarios et Services).
A4: 1. Scénarios retenus (20)
A5: Niveau de gravité | B5: Actuel | C5: Après plan (cibles à 3) | D5: À terme (cibles à 4)
A6: Niveau 4 | B6: =COUNTIF('Scénarios retenus'!$N$5:$N$24,4) -> 1 | C6: =COUNTIF('Scénarios retenus'!$Q$5:$Q$24,4) -> 0 | D6: =COUNTIF('Scénarios retenus'!$R$5:$R$24,4) -> 0
A7: Niveau 3 | B7: =COUNTIF('Scénarios retenus'!$N$5:$N$24,3) -> 18 | C7: =COUNTIF('Scénarios retenus'!$Q$5:$Q$24,3) -> 13 | D7: =COUNTIF('Scénarios retenus'!$R$5:$R$24,3) -> 2
A8: Niveau 2 | B8: =COUNTIF('Scénarios retenus'!$N$5:$N$24,2) -> 1 | C8: =COUNTIF('Scénarios retenus'!$Q$5:$Q$24,2) -> 7 | D8: =COUNTIF('Scénarios retenus'!$R$5:$R$24,2) -> 14
A9: Niveau 1 | B9: =COUNTIF('Scénarios retenus'!$N$5:$N$24,1) -> 0 | C9: =COUNTIF('Scénarios retenus'!$Q$5:$Q$24,1) -> 0 | D9: =COUNTIF('Scénarios retenus'!$R$5:$R$24,1) -> 4
A10: Total | B10: =SUM(B6:B9) -> 20 | C10: =SUM(C6:C9) -> 20 | D10: =SUM(D6:D9) -> 20
A11: Niveau ≥ 3 (inacceptable) | B11: =B6+B7 -> 19 | C11: =C6+C7 -> 13 | D11: =D6+D7 -> 2
A13: 2. Base complète du classeur (183 scénarios) — indicatif, non présenté à la direction
A14: Niveau de gravité | B14: Intrinsèque = actuel | C14: Après plan (cibles à 3) | D14: À terme (cibles à 4)
A15: Niveau 4 | B15: 1 | C15: 0 | D15: 0
A16: Niveau 3 | B16: 74 | C16: 51 | D16: 28
A17: Niveau 2 | B17: 77 | C17: 97 | D17: 98
A18: Niveau 1 | B18: 0 | C18: 4 | D18: 26
A19: Non évalué (actif non coté) | B19: 31 | C19: 31 | D19: 31
A20: Total | B20: =SUM(B15:B19) -> 183 | C20: =SUM(C15:C19) -> 183 | D20: =SUM(D15:D19) -> 183
A21: Niveau ≥ 3 (inacceptable) | B21: =B15+B16 -> 75 | C21: =C15+C16 -> 51 | D21: =D15+D16 -> 28
A22: Source : feuille Scénarios, col. Z, copies recalculées du classeur v04 (options 2 et 3), avec tous les scénarios sélectionnés (col. I à 1). Les 31 « non évalués » portent sur des actifs non cotés (D03, D05, P02). Comptage indicatif : seuls 35 sous-services sur 153 sont audités. Les scénarios non retenus qui restent inadmissibles sont listés dans l'onglet « Risques résiduels ».
A24: 3. Sous-services audités (35) — feuille Services
A25: Sous-service | B25: Intitulé | C25: Questions répondues | D25: Note V1 (col. D) | E25: Niveau final (col. J)
A26: 1B02 | B26: Utilisation des mobiles et télétravail | C26: 3 | D26: 1 | E26: 1
A27: 1B05 | B27: Cloisonnement des réseaux | C27: 3 | D27: 0 | E27: 1
A28: 1B07 | B28: Sécurité de l'information dans l'utilisation de services en nuage | C28: 2 | D28: 0 | E28: 1
A29: 1C06 | B29: Protection contre l'hameçonnage (phishing) et abus de confiance | C29: 5 | D29: 0 | E29: 1
A30: 1E01 | B30: Plans de continuité de l'activité | C30: 17 | D30: 0 | E30: 1
A31: 1E03 | B31: Gestion du personnel et des partenaires ou prestataires stratégiques | C31: 8 | D31: 0 | E31: 1
A32: 2D01 | B32: Contrôle d'accès physique aux zones de bureaux sensibles | C32: 16 | D32: 0 | E32: 1
A33: 2D02 | B33: Détection des intrusions dans les zones de bureaux protégées | C33: 8 | D33: 0 | E33: 1
A34: 2D03 | B34: Surveillance des zones de bureaux protégées | C34: 7 | D34: 0 | E34: 1
A35: 3A02 | B35: Gestion des autorisations d'accès (attribution, délégation, retrait) | C35: 14 | D35: 0 | E35: 1
A36: 3A03 | B36: Informations d'authentification | C36: 2 | D36: 0 | E36: 1
A37: 3A04 | B37: Contrôle des accès (aux applications, aux données applicatives et aux fonctions systèmes) | C37: 26 | D37: 0.21 | E37: 1
... A60: 8A01 | B60: Mise en place des processus et procédures adaptés aux exigences légales ou contractuelles | C60: 15 | D60: 0 | E60: 1
A61: Total questions | C61: =SUM(C26:C60) -> 300
A62: 300 réponses fondées sur l'énoncé ou sur une hypothèse tracée (règle R-21 du journal). Tous les sous-services restent au niveau 1, sauf 6B04 (niveau 2) : les questions de MEHARI portent sur le pilotage, la vérification et la copie hors site, et le niveau final ne descend jamais sous 1 (journal O-16).
A64: 4. Évolution prévue des 20 scénarios retenus (fin des projets, cibles à 3)
A65: Niveau de gravité | B65: Aujourd'hui | C65: Fin du mois 2 | D65: Fin du mois 4 | E65: Fin du mois 6
A66: Niveau 4 | B66: 1 | C66: 0 | D66: 0 | E66: 0
A67: Niveau 3 | B67: 18 | C67: 16 | D67: 13 | E67: 13
A68: Niveau 2 | B68: 1 | C68: 4 | D68: 7 | E68: 7
A69: Niveau 1 | B69: 0 | C69: 0 | D69: 0 | E69: 0
A70: Projets terminés : fin du mois 2 = SADC, PMAL, CASE ; fin du mois 4 = tous sauf SUAI ; fin du mois 6 = les 12 projets. Simulation sur copies du classeur (option 3), en supposant les cibles atteintes à la date de fin de chaque projet. Le Tbord du classeur donne la même information par années, sa macro fixant les dates au 1er janvier (journal O-23).

Sheet Scénarios exclus
A1: Scénarios non retenus (163) — exclusion explicite (étape 19)
A2: Catégorie attribuée par règle à partir du classeur, puis relue scénario par scénario : « levier commun » n'est conservé que si un projet décidé agit sur le scénario (colonne I). Colonne H : gravité après le plan (classeur rendu, cibles à 3). Dans le classeur : Sélection (col. I) = 0.
A4: Réf. | B4: Ligne Scénarios | C4: Libellé MEHARI | D4: Gravité actuelle | E4: Catégorie | F4: Motif | G4: Services de réduction | H4: Gravité après plan (cibles à 3) | I4: Projets décidés agissant
A5: CEPD03-a | B5: 105 | C5: Destruction ou vol de courrier postal dans les locaux du courrier — par une personne non autorisée à pénétrer dans les locaux du courrier | D5: 3 | E5: Hors périmètre | F5: Courrier postal : le périmètre porte sur les services numériques (énoncé p.2) ; cohérent avec 1C06-02 = X | G5: 2B01, 2B02, 2E05 | H5: 3 | I5: aucun
A6: CEPD03-b | B6: 106 | C6: Destruction ou vol de courrier postal dans les locaux du courrier — par une personne autorisée à pénétrer dans les locaux du courrier (dont le personnel doté de droits privilégiés) | D6: 3 | E6: Hors périmètre | F6: Courrier postal : le périmètre porte sur les services numériques (énoncé p.2) ; cohérent avec 1C06-02 = X | G6: 2B03, 2E05 | H6: 3 | I6: aucun
A7: CEPD04 | B7: 107 | C7: Perte accidentelle de courrier postal reçu, dans le circuit de distribution interne. | D7: 3 | E7: Hors périmètre | F7: Courrier postal : le périmètre porte sur les services numériques (énoncé p.2) ; cohérent avec 1C06-02 = X | G7: 2E05 | H7: 3 | I7: aucun
A8: IEID01-a | B8: 89 | C8: Vol physique de document — dans un bureau par une personne autorisée à y pénétrer (dont personnel doté de droits d'accès physiques privilégiés) | D8: — | E8: Non évalué | F8: Actif D03 désélectionné dans Classif (aucun document papier dans l'énoncé) | G8: 2D03, 2E01 | H8: — | I8: aucun
A9: IEID01-b | B9: 90 | C9: Vol physique de document — dans un bureau par une personne non autorisée à y pénétrer | D9: — | E9: Non évalué | F9: Actif D03 désélectionné dans Classif (aucun document papier dans l'énoncé) | G9: 2D01, 2D02, 2D03, 2D04, 2E01 | H9: — | I9: aucun
A10: IEID01-c | B10: 91 | C10: Vol physique de document — lors d'une impression sur imprimante partagée | D10: — | E10: Non évalué | F10: Actif D03 désélectionné dans Classif (aucun document papier dans l'énoncé) | G10: 6B05 | H10: — | I10: aucun
A11: IEID02 | B11: 92 | C11: Accident grave dû à l'environnement (Incendie, Inondation, foudroiement, etc.) ou à des actes de terrorisme | D11: — | E11: Non évalué | F11: Actif D03 désélectionné dans Classif (aucun document papier dans l'énoncé) | G11: 2A03, 2E01 | H11: — | I11: aucun
A12: IEID03 | B12: 93 | C12: Incident dû à l'environnement (Dégât des eaux, vieillissement, pollution, surcharge électrique, etc.) ou à du vandalisme | D12: — | E12: Non évalué | F12: Actif D03 désélectionné dans Classif (aucun document papier dans l'énoncé) | G12: 2E01 | H12: — | I12: aucun
A13: IEII01 | B13: 95 | C13: Falsification ou remplacement par un faux | D13: — | E13: Non évalué | F13: Actif D03 désélectionné dans Classif (aucun document papier dans l'énoncé) | G13: 2D01, 2D02, 2D03, 2D04, 2E01 | H13: — | I13: aucun
A14: IEIC01-a | B14: 97 | C14: Vol physique ou copie de document — dans un bureau par une personne non autorisée | D14: — | E14: Non évalué | F14: Actif D03 désélectionné dans Classif (aucun document papier dans l'énoncé) | G14: 2D01, 2D02, 2D03, 2D04, 2E01 | H14: — | I14: aucun
A15: IEIC01-b | B15: 98 | C15: Vol physique ou copie de document — dans un bureau par une personne autorisée à y pénétrer (dont personnel doté de droits d'accès physiques privilégiés) | D15: — | E15: Non évalué | F15: Actif D03 désélectionné dans Classif (aucun document papier dans l'énoncé) | G15: 2D03, 2E01 | H15: — | I15: aucun
A16: IEIC01-c | B16: 99 | C16: Vol physique ou copie de document — lors d'une impression sur imprimante partagée | D16: — | E16: Non évalué | F16: Actif D03 désélectionné dans Classif (aucun document papier dans l'énoncé) | G16: 6B05 | H16: — | I16: aucun
A17: IEIC01-d | B17: 100 | C17: Vol physique ou copie de document — récupération de brouillon de document ou de document mis au rebut | D17: — | E17: Non évalué | F17: Actif D03 désélectionné dans Classif (aucun document papier dans l'énoncé) | G17: 2E02 | H17: — | I17: aucun
A18: IEIC02 | B18: 101 | C18: Consultation de document sensible par une personne non autorisée à pénétrer dans les espaces de bureau | D18: — | E18: Non évalué | F18: Actif D03 désélectionné dans Classif (aucun document papier dans l'énoncé) | G18: 2D01, 2D02, 2D04, 2E01 | H18: — | I18: aucun
A19: ARCD01 | B19: 117 | C19: Effacement de fichier d'archive (effacement malveillant, par un utilisateur ou par une personne dotée de droits privilégiés ) | D19: — | E19: Non évalué | F19: Actif D05 désélectionné dans Classif (aucune archive mentionnée) | G19: 3A08, 4A11, 4F02 | H19: — | I19: SUAI
... A38: PGDE03 | B38: 215 | C38: Application d'une procédure non adaptée aux règles de gouvernance, de décision et de contrôle (autre que celle qui aurait du être déclenchée) par incompréhension ou conflits entre procédures | D38: — | E38: Non évalué | F38: P02 non coté dans T2 et désélectionné dans Classif | G38: 8B03 | H38: — | I38: aucun
A39: DAPD10-a | B39: 19 | C39: Perte par vol physique de document ou de media — vol commis par une personne autorisée à pénétrer dans les locaux de l'exploitation (dont le personnel ayant des droits privilégiés) | D39: 3 | E39: Non prioritaire (physique) | F39: Événement physique ou environnemental : locaux non décrits dans l'énoncé, questionnaire 2 Phy non audité ; à traiter dans une itération ultérieure | G39: 2B03, 4A03 | H39: 2 | I39: SADC
A40: DAPD10-b | B40: 20 | C40: Perte par vol physique de document ou de media — vol commis par une personne non autorisée à pénétrer dans les locaux de l'exploitation | D40: 3 | E40: Non prioritaire (physique) | F40: Événement physique ou environnemental : locaux non décrits dans l'énoncé, questionnaire 2 Phy non audité ; à traiter dans une itération ultérieure | G40: 2B01, 2B02, 4A03 | H40: 2 | I40: SADC
A41: DAPD11 | B41: 21 | C41: Incident dû à l'environnement (Dégât des eaux, vieillissement, pollution, surcharge électrique, etc.) ou à du vandalisme | D41: 3 | E41: Non prioritaire (physique) | F41: Événement physique ou environnemental : locaux non décrits dans l'énoncé, questionnaire 2 Phy non audité ; à traiter dans une itération ultérieure | G41: 4A03, 4E02 | H41: 2 | I41: SADC
A42: DAPD12 | B42: 22 | C42: Accident grave dû à l'environnement (Incendie, Inondation, foudroiement, etc.) ou à des actes de terrorisme | D42: 3 | E42: Non prioritaire (physique) | F42: Incendie ou accident grave : le plan le ramène à 2 grâce à la copie hors site et hors ligne des sauvegardes (A05, projet SADC, H-19) ; locaux décrits seulement en partie (H-29), sécurité physique hors de la priorité du plan. | G42: 2A03, 4A03, 4E02 | H42: 2 | I42: SADC
A43: DAPI05-a | B43: 34 | C43: Echange physique (avec un média au contenu modifié) — dans les locaux de l'exploitation, par une personne autorisée à y pénétrer (dont le personnel ayant des droits privilégiés) | D43: 3 | E43: Non prioritaire (physique) | F43: Événement physique ou environnemental : locaux non décrits dans l'énoncé, questionnaire 2 Phy non audité ; à traiter dans une itération ultérieure | G43: 2B03, 5A02, 5A03, 5B02 | H43: 3 | I43: aucun
A44: DAPI05-b | B44: 35 | C44: Echange physique (avec un média au contenu modifié) — dans les locaux de l'exploitation, par ure personne non autorisée | D44: 3 | E44: Non prioritaire (physique) | F44: Événement physique ou environnemental : locaux non décrits dans l'énoncé, questionnaire 2 Phy non audité ; à traiter dans une itération ultérieure | G44: 2B01, 2B03, 5A02, 5A03, 5B02 | H44: 3 | I44: aucun
A45: DAPC04-a | B45: 42 | C45: Vol physique ou duplication de média support de données — dans les locaux de l'exploitation, par une personne autorisée (dont le personnel ayant des droits privilégiés) | D45: 3 | E45: Non prioritaire (physique) | F45: Événement physique ou environnemental : locaux non décrits dans l'énoncé, questionnaire 2 Phy non audité ; à traiter dans une itération ultérieure | G45: 2B03, 5B02 | H45: 3 | I45: aucun
A46: DAPC04-b | B46: 43 | C46: Vol physique ou duplication de média support de données — dans les locaux de l'exploitation, par une personne non autorisée | D46: 3 | E46: Non prioritaire (physique) | F46: Événement physique ou environnemental : locaux non décrits dans l'énoncé, questionnaire 2 Phy non audité ; à traiter dans une itération ultérieure | G46: 2B01, 2B02, 5B02 | H46: 3 | I46: aucun
A47: DBUC09 | B47: 84 | C47: Captation de données ponctuelles par dispositif physique Capteur de frappe ou "Keylogger" | D47: 3 | E47: Non prioritaire (physique) | F47: Événement physique ou environnemental : locaux non décrits dans l'énoncé, questionnaire 2 Phy non audité ; à traiter dans une itération ultérieure | G47: 2D01, 2D02, 2D03, 6A01 | H47: 3 | I47: aucun
A48: DBUC10-c | B48: 87 | C48: Vol physique ou duplication — lors de la mise au rebut d'un media | D48: 3 | E48: Non prioritaire (physique) | F48: Événement physique ou environnemental : locaux non décrits dans l'énoncé, questionnaire 2 Phy non audité ; à traiter dans une itération ultérieure | G48: 4E03, 6B01 | H48: 3 | I48: CHDB
A49: DBUC10-a | B49: 85 | C49: Vol physique ou duplication — dans les bureaux, par une personne autorisée (dont le personnel doté de droits privilégiés) | D49: 3 | E49: Levier commun | F49: Même événement que DBUC10-b (retenu, H-28), commis par une personne autorisée ; même levier de prévention (6B01, projet CHDB). Reste au niveau 3 après le plan avec des cibles à 3 : risque résiduel (onglet Risques résiduels). | G49: 2D03, 6B01 | H49: 3 | I49: CHDB
A50: DAPD01-a | B50: 6 | C50: Effacement malveillant de données — par un utilisateur autorisé (dont le personnel ayant des droits privilégiés) | D50: 3 | E50: Levier commun | F50: Partage au moins un service de réduction avec un scénario retenu (DAPD02, DAPD03, DAPI01-b) : bénéficie en partie des mêmes projets ; non retenu pour garder une sélection courte | G50: 3A08, 4A03, 4A11 | H50: 2 | I50: SADC, SUAI
... A167: PGCE03 | B167: 211 | C167: Application d'une procédure inadaptée au respect des exigences légales ou contractuelles (autre que celle qui aurait du être déclenchée) par incompréhension ou conflits entre procédures | D167: 2 | E167: Gravité tolérée | F167: Gravité actuelle 2 : risque toléré selon la grille (guide p.16) | G167: 8A03 | H167: 2 | I167: CPEX
A169: Comptage
C170: Hors périmètre | D170: =COUNTIF($E$5:$E$167,C170) -> 3
C171: Non évalué | D171: =COUNTIF($E$5:$E$167,C171) -> 31
C172: Non prioritaire (physique) | D172: =COUNTIF($E$5:$E$167,C172) -> 10
C173: Levier commun | D173: =COUNTIF($E$5:$E$167,C173) -> 23
C174: Non prioritaire | D174: =COUNTIF($E$5:$E$167,C174) -> 20
C175: Gravité tolérée | D175: =COUNTIF($E$5:$E$167,C175) -> 76
