Workbook

Sheet Lisez-moi
A1: Journal d'hypothèses - TP MEHARI, Alsace Formation Numérique (AFN)
A2: Version 11 du 23/10/2026 — auteurs : Kleiton KITANI, Ryan AMORY. À utiliser avec le classeur AFN_MEHARI_v04_2026-10-20.xlsm (20 scénarios retenus, 8 risques prioritaires, 12 projets décidés, cibles à 3).
A4: Contenu
A5: Journal : le journal lui-même. Les colonnes A à D suivent le modèle imposé par l'énoncé (§7, p.5) : Réf., Hypothèse / observation, Impact sur l'analyse, Validation requise.
A6: Règles de méthode : ce que l'énoncé, l'introduction aux TP et le guide MEHARI demandent de tracer, avec la page, et les règles de l'équipe (R-21 à R-23).
A7: Synthèse : comptage automatique des entrées, par type et par statut.
A9: Rôles de l'équipe (étape 2)
A10: Binôme : Kleiton KITANI et Ryan AMORY. Pilote de l'analyse : Kleiton KITANI Responsable actifs et enjeux : Ryan AMORY Responsable diagnostic et risques : Kleiton KITANI Responsable restitution : Ryan AMORY
A12: Ce qui est dans le journal
A13: O-01 à O-12 : observations tirées de l'énoncé ou du classeur. O-13 : paramètre modifié dans le classeur (option de gravité). O-14 : lignes de périmètre de T1 et T2 (domaines 7, 9, 10, processus 2), conservées. O-15 : lecture du sous-service 3A09 et rattachement du projet CASE. O-16 : écarts entre l'échelle de l'énoncé et les niveaux MEHARI, et test de la note directe. O-17 : révision de la sélection (DBUC05, CEPI02 ; SEXD01 regroupé). O-18 : décisions du plan (12 projets) et résultat du Tbord. O-19 et O-20 : défauts du modèle CLUSIF. O-21 : couverture et ordre du diagnostic. O-22 : Plans_action (sélections et renvois en colonne AL). O-23 : échéancier annuel du Tbord. O-24 : risques résiduels hors sélection. O-25 : feuille Score ISO 27002. O-26 : deux réponses à revoir (4A02-01, 4A03-01). H-01 à H-03 : exemples d'hypothèses donnés par l'énoncé. H-04 à H-06 : notes de lecture de l'équipe. H-07 à H-13 : hypothèses du plan de traitement. H-14 et H-15 : désélections de Classif (archives D05, gouvernance P02). H-16 à H-29 : hypothèses de maturité ; elles donnent, pour chaque question, la réponse saisie. H-30 à H-36 : messagerie et fraude au RIB, objectifs de reprise, effet estimé de A01 et A10, phase 2, critère d'acceptation proposé, NIS2, RGPD. J-01 à J-11 : justifications des niveaux de T1 et T2. M-01 à M-12 : informations manquantes ; la colonne E renvoie à l'hypothèse qui couvre chacune. Q-01 : question à l'enseignant (notation de 0 à 4, variante V1 et note directe).
A15: Résultats du classeur v04
A16: Sous-services : tous au niveau 1, sauf 6B04 (niveau 2). La gravité actuelle reste égale à la gravité intrinsèque (O-16). Tbord : aujourd'hui, 19 scénarios inacceptables sur 20. Après le plan (12 projets, cibles à 3) : 0 au niveau 4, 11 au niveau 3, 7 au niveau 2, plus les 2 acceptés de RP-6 : 13 inacceptables. Avec des cibles à 4 (copie) : 2. Hors sélection : 56 scénarios de gravité 3 aujourd'hui, 38 après le plan (O-24).
... A25: Énoncé « TP MEHARI – Analyse de risques SSI » « Introduction aux TP : analyse de risques, audit SSI et gouvernance cyber » CLUSIF, « MEHARI–Standard 2022, Guide de l'utilisateur », Éd. 2, août 2022 Cours « Cybersécurité : normes et standards » BUT3 v2026 Classeur DB-Standard-2022-Ed.2.1 (formules des feuilles Services et Scénarios) Notes de lecture de l'équipe sur l'énoncé. Dossier d'analyse MEHARI — AFN ; AFN_Registre_risques_et_feuille_de_route_v5.xlsx.

Sheet Journal
A1: Réf. | B1: Hypothèse / observation | C1: Impact sur l'analyse | D1: Type | E1: Validation requise | F1: Statut | G1: Correspondance classeur | H1: Source exacte
A2: O-01 | B2: AFN est une PME fictive qui conçoit et dispense des formations professionnelles hybrides ; elle emploie 45 personnes et accueille environ 1 200 apprenants par an. | C2: Contexte à présenter dans le dossier (partie 2). | D2: Observation | E2: Aucune (donnée de l'énoncé). | F2: Fait établi | G2: — | H2: Énoncé TP, §3, p.1
A3: O-02 | B3: Services numériques exploités : site vitrine, plateforme LMS, messagerie collaborative, CRM, stockage cloud, solution de facturation, postes de travail administratifs. | C3: Candidats aux actifs à sélectionner dans Classif (étape 10 : « types d'actifs réellement pertinents »). | D3: Observation | E3: Aucune (donnée de l'énoncé). | F3: Fait établi | G3: Classif | H3: Énoncé TP, §3, p.1
A4: O-03 | B4: Données traitées : identités et coordonnées des apprenants, dossiers de financement, feuilles d'émargement, résultats d'évaluation, contrats, factures, données RH. | C4: À classer dans T1 (données) ; chaque niveau élevé doit être justifié (étape 12). | D4: Observation | E4: Aucune (donnée de l'énoncé). | F4: Fait établi | G4: T1 | H4: Énoncé TP, §3 « Contexte et contraintes », p.2
A5: O-04 | B5: La plateforme LMS, les visioconférences et la messagerie sont indispensables pendant les périodes de formation. | C5: Élément utilisable pour justifier une disponibilité élevée ; l'exemple de l'énoncé cote la LMS « D élevée » (p.3). | D5: Observation | E5: Durée d'interruption tolérable non précisée : voir M-07. | F5: Fait établi | G5: T1 / T2 | H5: Énoncé TP, §3, p.2
A6: O-05 | B6: Une partie des services est hébergée chez des prestataires cloud ; l'entreprise dispose aussi d'un NAS local et de quelques serveurs virtuels. | C6: Concerne les actifs « Services externalisés ou hébergés sur le cloud » et « Données externalisées sur le cloud » de Classif. | D6: Observation | E6: Services concernés non précisés : voir M-01. | F6: Fait établi | G6: Classif S02, D07 ; services 1B07, 3A09, 4A03, 4A04, 5D02 (par intitulé) | H6: Énoncé TP, §3, p.2
A7: O-06 | B7: Le télétravail est autorisé. | C7: Lié au périmètre « accès distant » (p.2). | D7: Observation | E7: Mode d'accès distant non décrit : voir M-02. | F7: Fait établi | G7: Services 1B02 « Télétravail », 6A02 « Travail en dehors des locaux » (par intitulé) | H7: Énoncé TP, §3, p.2
A8: O-07 | B8: Les comptes administrateurs et les comptes de formateurs disposent de droits variables selon les applications. | C8: Lié au périmètre « comptes à privilèges » (p.2). | D8: Observation | E8: Règles d'attribution non décrites : voir M-04. | F8: Fait établi | G8: Services 3A02, 3A06, 3A07, 3A08 (par intitulé) | H8: Énoncé TP, §3, p.2
A9: O-08 | B9: La direction souhaite renforcer la résilience après plusieurs incidents mineurs : hameçonnage, indisponibilité d'un outil SaaS, erreurs de partage de fichiers, absence ponctuelle de sauvegardes vérifiées. | C9: L'énoncé (§7, p.5) en tire trois risques exemples : R-01 compromission d'un compte via hameçonnage (LMS, comptes formateurs) ; R-02 divulgation par partage cloud mal configuré (dossiers apprenants) ; R-03 indisponibilité d'un service SaaS critique (continuité des formations). | D9: Observation | E9: Date, fréquence et conséquences non précisées : voir M-06. | F9: Fait établi | G9: Scénarios dont l'intitulé correspond : DBUC03 (hameçonnage), DBUC02 (diffusion accidentelle d'un fichier), SEXD02 (arrêt de l'infrastructure des services externalisés) ; service 1C06 | H9: Énoncé TP, §3 p.2 ; §7 « Registre des risques prioritaires » p.5
A10: O-09 | B10: Les moyens financiers sont limités : les recommandations doivent être priorisées et proportionnées. | C10: Le coût des actions s'exprime en faible / moyen / élevé (étape 25, p.4). | D10: Observation | E10: Montant non précisé : voir M-08. | F10: Fait établi | G10: Plans_action, Projets | H10: Énoncé TP, §3, p.2
A11: O-10 | B11: Périmètre minimal obligatoire : inscription et gestion administrative des apprenants ; délivrance des formations à distance ou hybrides ; données personnelles, contractuelles et financières ; messagerie, stockage collaboratif, LMS et accès distant ; postes de travail, comptes à privilèges, sauvegardes et équipements réseau essentiels. | C11: Tout scénario hors de ce périmètre doit être exclu explicitement (étape 19, p.3). | D11: Observation | E11: Aucune (donnée de l'énoncé). | F11: Fait établi | G11: T1, Scénarios | H11: Énoncé TP, §3 « Périmètre minimal obligatoire », p.2
A12: O-11 | B12: Le classeur utilisé est MEHARI–Standard 2022, édition 2.1 (10/08/2022). | C12: Citer la version exacte dans la partie « Méthode suivie » du dossier (étape 30). | D12: Observation | E12: Aucune. | F12: Fait établi | G12: Intro | H12: Classeur, onglet Intro ; cours normes p.68–69 (« Conserver la traçabilité de la version utilisée »)
... A87: Q-01 | B87: L'étape 15 demande une note de 0 à 4 par contrôle, alors que la variante V1 du classeur attend une réponse par question (1 = oui, 0 = non, X = sans objet) et calcule elle-même la note de 0 à 4 de chaque sous-service (feuille Services). Le classeur permet aussi de saisir une note directe de 0 à 4 sur la ligne d'en-tête d'un sous-service (la formule de Services, colonne D, lit d'abord cette cellule). Interprétation retenue : réponses 1 / 0 / X par question, note de 0 à 4 lue dans Services. | C87: Conditionne la notation de toutes les questions (R-10, R-11, R-21). La note directe a été testée sur une copie avec l'échelle de l'énoncé : niveaux et gravités identiques (O-16). La variante V1 est gardée parce qu'elle trace la réponse à chaque question. | D87: Question enseignant | E87: À confirmer par l'enseignant. | F87: Hypothèse | G87: Questionnaires 1 à 8, colonne C (lignes de questions et lignes d'en-tête) ; Services, colonnes D et H. | H87: Énoncé p.3, étape 15 ; classeur, feuille Services.

Sheet Règles de méthode
A1: Réf. | B1: Règle | C1: Source exacte
A2: R-01 | B2: Toute information absente du cas doit être formulée explicitement comme hypothèse. | C2: Énoncé p.2, étape 5
A3: R-02 | B3: Ouvrir un journal d'hypothèses, de questions et d'informations manquantes. | C3: Introduction aux TP p.18–19
A4: R-03 | B4: Quatre statuts : fait établi (preuve identifiable), déclaration (sans preuve complémentaire), hypothèse (interprétation à confirmer), information manquante (nécessaire mais indisponible). Ne jamais transformer une déclaration ou une hypothèse en fait établi. | C4: Introduction aux TP p.14
A5: R-04 | B5: Ne pas inventer de preuves, de sources ou d'éléments factuels pour compléter le cas. | C5: Introduction aux TP p.21
A6: R-05 | B6: Une absence de preuve n'est pas une preuve d'absence : qualifier l'information comme manquante et indiquer ce qu'il faudrait vérifier. | C6: Introduction aux TP p.13
A7: R-06 | B7: Justifier chaque niveau élevé de disponibilité, intégrité ou confidentialité dans le journal d'hypothèses. | C7: Énoncé p.3, étape 12
A8: R-07 | B8: Une cotation élevée doit renvoyer à une conséquence concrète (interruption d'activité, perte ou divulgation de données, retard de formation ou de facturation, non-respect d'une obligation, perte financière, atteinte à l'image…). | C8: Introduction aux TP p.15 ; énoncé §9 p.6
A9: R-08 | B9: Échelle de gravité : décrire avec des exemples les impacts faible, modéré, important et critique. Le guide recommande de fixer pour chaque dysfonctionnement les paramètres et seuils qui font passer d'un niveau à l'autre. | C9: Énoncé p.3, étape 9 ; guide p.30 (7.2)
A10: R-09 | B10: Dans T1 / T2, une case à 1 génère des scénarios d'impact non significatif ; une case vide n'en génère aucun. | C10: Guide p.34 (8.5.1)
A11: R-10 | B11: Choisir une seule variante de notation (V1, V2, V3 ou V4) et l'utiliser uniformément. Si plusieurs variantes sont remplies, l'onglet Services retient le minimum. | C11: Énoncé p.3, étape 13 ; guide p.35–36 (9.2.1, 9.3)
A12: R-11 | B12: Notes 0 à 4 : 0 inexistant, 1 partiel, 2 en place mais incomplet, 3 correctement mis en œuvre, 4 mature et documenté. | C12: Énoncé p.3, étape 15 (voir Q-01)
... A24: R-23 | B24: Colonnes V et W de la feuille Scénarios (« I décidé », « P décidée ») : elles remplacent l'impact et la potentialité calculés dans toutes les options de gravité, actuelle comme résiduelle. On ne les utilise que pour corriger l'état actuel, quand une mesure existante n'est pas modélisée par la base, avec une entrée au journal. L'effet d'une mesure prévue mais non modélisée est estimé hors classeur, dans le registre, avec son motif : A08 sur DBUC02 et DEXC01 (H-27), A01 et A10 sur DAPC01-a et DAPI01-b (H-32). | C24: Classeur, feuille Scénarios (formule de la colonne Z) ; énoncé §9 p.6 (tracer toute modification)

Sheet Synthèse
A1: Synthèse du journal
A2: Calculée automatiquement à partir de l'onglet Journal.
A4: Type | B4: Fait établi | C4: Déclaration | D4: Hypothèse | E4: Information manquante | F4: Total
A5: Observation | B5: =COUNTIFS(Journal!$D$2:$D$100,$A5,Journal!$F$2:$F$100,B$4) -> 26 | C5: =COUNTIFS(Journal!$D$2:$D$100,$A5,Journal!$F$2:$F$100,C$4) -> 0 | D5: =COUNTIFS(Journal!$D$2:$D$100,$A5,Journal!$F$2:$F$100,D$4) -> 0 | E5: =COUNTIFS(Journal!$D$2:$D$100,$A5,Journal!$F$2:$F$100,E$4) -> 0 | F5: =SUM(B5:E5) -> 26
A6: Hypothèse | B6: =COUNTIFS(Journal!$D$2:$D$100,$A6,Journal!$F$2:$F$100,B$4) -> 0 | C6: =COUNTIFS(Journal!$D$2:$D$100,$A6,Journal!$F$2:$F$100,C$4) -> 0 | D6: =COUNTIFS(Journal!$D$2:$D$100,$A6,Journal!$F$2:$F$100,D$4) -> 36 | E6: =COUNTIFS(Journal!$D$2:$D$100,$A6,Journal!$F$2:$F$100,E$4) -> 0 | F6: =SUM(B6:E6) -> 36
A7: Justification DIC | B7: =COUNTIFS(Journal!$D$2:$D$100,$A7,Journal!$F$2:$F$100,B$4) -> 3 | C7: =COUNTIFS(Journal!$D$2:$D$100,$A7,Journal!$F$2:$F$100,C$4) -> 0 | D7: =COUNTIFS(Journal!$D$2:$D$100,$A7,Journal!$F$2:$F$100,D$4) -> 8 | E7: =COUNTIFS(Journal!$D$2:$D$100,$A7,Journal!$F$2:$F$100,E$4) -> 0 | F7: =SUM(B7:E7) -> 11
A8: Information manquante | B8: =COUNTIFS(Journal!$D$2:$D$100,$A8,Journal!$F$2:$F$100,B$4) -> 0 | C8: =COUNTIFS(Journal!$D$2:$D$100,$A8,Journal!$F$2:$F$100,C$4) -> 0 | D8: =COUNTIFS(Journal!$D$2:$D$100,$A8,Journal!$F$2:$F$100,D$4) -> 0 | E8: =COUNTIFS(Journal!$D$2:$D$100,$A8,Journal!$F$2:$F$100,E$4) -> 12 | F8: =SUM(B8:E8) -> 12
A9: Question enseignant | B9: =COUNTIFS(Journal!$D$2:$D$100,$A9,Journal!$F$2:$F$100,B$4) -> 0 | C9: =COUNTIFS(Journal!$D$2:$D$100,$A9,Journal!$F$2:$F$100,C$4) -> 0 | D9: =COUNTIFS(Journal!$D$2:$D$100,$A9,Journal!$F$2:$F$100,D$4) -> 1 | E9: =COUNTIFS(Journal!$D$2:$D$100,$A9,Journal!$F$2:$F$100,E$4) -> 0 | F9: =SUM(B9:E9) -> 1
A10: Total | B10: =SUM(B5:B9) -> 29 | C10: =SUM(C5:C9) -> 0 | D10: =SUM(D5:D9) -> 45 | E10: =SUM(E5:E9) -> 12 | F10: =SUM(F5:F9) -> 86

Sheet Listes
A1: Type | B1: Statut | C1: État
A2: Observation | B2: Fait établi | C2: À valider
A3: Hypothèse | B3: Déclaration | C3: Validé équipe
A4: Justification DIC | B4: Hypothèse | C4: Confirmé enseignant
A5: Information manquante | B5: Information manquante | C5: Clos
A6: Question enseignant
